Workbook

Sheet Actors Reference
A1: DRAMOIR · Actors Reference
A2: Actor Name | B2: Photo URL | C2: Dramas
A3: Ahn Bo-Hyun | B3: https://pin.it/3Md90mGxp | C3: {=TEXTJOIN(", ", TRUE, IF(ISNUMBER(SEARCH(A3, 'Kdrama Database '!$G$3:$G$1010)), 'Kdrama Database '!$A$3:$A$1010, ""))} -> Dokgo rewind , Flex x cop, Flex x cop 2, Her private life, Itaewon class, Kairos, Military prosecutor doberman, My name, See you in my 19th life, Spring fever, Wednesday 3:30 PM, Yumi's cells, Yumi's cells 2
A4: Ahn Eun-Jin | B4: https://pin.it/6kFqIqieH | C4: {=TEXTJOIN(", ", TRUE, IF(ISNUMBER(SEARCH(A4, 'Kdrama Database '!$G$3:$G$1010)), 'Kdrama Database '!$A$3:$A$1010, ""))} -> Dynamite kiss, Genie, make a wish, Good casting, Goodbye earth , Hospital playlist 2, My dearest, Strangers from hell, The good bad mom, The one and only
A5: Ahn Hee-Yeon | B5: https://pin.it/5urRceX6H | C5: {=TEXTJOIN(", ", TRUE, IF(ISNUMBER(SEARCH(A5, 'Kdrama Database '!$G$3:$G$1010)), 'Kdrama Database '!$A$3:$A$1010, ""))} -> Call it love, Idol: the coup, Love Alarm 2, Not yet thirty, XX
A6: Ahn Hyo-Seop | B6: https://pin.it/6VISaL2Yu | C6: {=TEXTJOIN(", ", TRUE, IF(ISNUMBER(SEARCH(A6, 'Kdrama Database '!$G$3:$G$1010)), 'Kdrama Database '!$A$3:$A$1010, ""))} -> A business proposal, A time called you, Abyss, Dr. Romantic 2, Dr. Romantic 3, Haechi, Lovers of the red sky, Queen of the ring, Sold out on you, Splash Splash love, Still 17
A7: Ahn Jae Hyun | B7: https://pin.it/7ttZ6ExVs | C7: {=TEXTJOIN(", ", TRUE, IF(ISNUMBER(SEARCH(A7, 'Kdrama Database '!$G$3:$G$1010)), 'Kdrama Database '!$A$3:$A$1010, ""))} -> Cinderella and the four knights, The beauty inside
A8: Ahn Jae-Hong | B8: https://pin.it/59Qh70irf | C8: {=TEXTJOIN(", ", TRUE, IF(ISNUMBER(SEARCH(A8, 'Kdrama Database '!$G$3:$G$1010)), 'Kdrama Database '!$A$3:$A$1010, ""))} -> Be melodramatic, Bloodhounds 2, Fight for my way, Mask girl, Reply 1988
A9: Ahn Ji-Ho | B9: https://pin.it/3RsNBTGW3 | C9: {=TEXTJOIN(", ", TRUE, IF(ISNUMBER(SEARCH(A9, 'Kdrama Database '!$G$3:$G$1010)), 'Kdrama Database '!$A$3:$A$1010, ""))} -> Begins ≠ Youth, Night has come, Nobody knows, The defects
A10: Ahn Seung-Gyun | B10: https://share.google/OHfLq0dBoSua2tNSB | C10: {=TEXTJOIN(", ", TRUE, IF(ISNUMBER(SEARCH(A10, 'Kdrama Database '!$G$3:$G$1010)), 'Kdrama Database '!$A$3:$A$1010, ""))} -> 365: repeat the year, Still 17
A11: Ahn Si-Eun | B11: https://share.google/wzrJr0vyyPofgRUXM | C11: {=TEXTJOIN(", ", TRUE, IF(ISNUMBER(SEARCH(A11, 'Kdrama Database '!$G$3:$G$1010)), 'Kdrama Database '!$A$3:$A$1010, ""))} -> Dr. Romantic 2, Flower ever after, You are my spring
A12: Ahn So-Hee | B12: https://pin.it/2whf6WGmH | C12: {=TEXTJOIN(", ", TRUE, IF(ISNUMBER(SEARCH(A12, 'Kdrama Database '!$G$3:$G$1010)), 'Kdrama Database '!$A$3:$A$1010, ""))} -> Missing: the other side, Missing: the other side 2, Welcome to waikiki 2
A13: Arin | B13: https://pin.it/7BuAOFW4E | C13: {=TEXTJOIN(", ", TRUE, IF(ISNUMBER(SEARCH(A13, 'Kdrama Database '!$G$3:$G$1010)), 'Kdrama Database '!$A$3:$A$1010, ""))} -> My girlfriend is the man, S line
A14: Asahi | B14: https://pin.it/2M4y8UERC | C14: {=TEXTJOIN(", ", TRUE, IF(ISNUMBER(SEARCH(A14, 'Kdrama Database '!$G$3:$G$1010)), 'Kdrama Database '!$A$3:$A$1010, ""))} -> The mysterious class
... A120: Esom | B120: https://pin.it/7GEL1xnr0 | C120: {=TEXTJOIN(", ", TRUE, IF(ISNUMBER(SEARCH(A120, 'Kdrama Database '!$G$3:$G$1010)), 'Kdrama Database '!$A$3:$A$1010, ""))} -> Because this is my first life, Black knight , Phantom lawyer, Save me 2, Taxi driver
A121: Geum Hae-Na | C121: {=TEXTJOIN(", ", TRUE, IF(ISNUMBER(SEARCH(A121, 'Kdrama Database '!$G$3:$G$1010)), 'Kdrama Database '!$A$3:$A$1010, ""))} -> A shop for killers
A122: Geum Sae-Rok | C122: {=TEXTJOIN(", ", TRUE, IF(ISNUMBER(SEARCH(A122, 'Kdrama Database '!$G$3:$G$1010)), 'Kdrama Database '!$A$3:$A$1010, ""))} -> Class of lies
A123: Gil Hae-Yeon | C123: {=TEXTJOIN(", ", TRUE, IF(ISNUMBER(SEARCH(A123, 'Kdrama Database '!$G$3:$G$1010)), 'Kdrama Database '!$A$3:$A$1010, ""))} -> Beyond evil , Doctor on the edge, Law school, The silent sea , The winning try
A124: Go Ah-Sung | C124: {=TEXTJOIN(", ", TRUE, IF(ISNUMBER(SEARCH(A124, 'Kdrama Database '!$G$3:$G$1010)), 'Kdrama Database '!$A$3:$A$1010, ""))} -> Life on mars
A125: Go Ara | C125: {=TEXTJOIN(", ", TRUE, IF(ISNUMBER(SEARCH(A125, 'Kdrama Database '!$G$3:$G$1010)), 'Kdrama Database '!$A$3:$A$1010, ""))} -> Black , Do do sol sol la la sol, Haechi, Hwarang: the beginning, The Scandal of Chunhwa
A126: Go Bo-Gyeol | C126: {=TEXTJOIN(", ", TRUE, IF(ISNUMBER(SEARCH(A126, 'Kdrama Database '!$G$3:$G$1010)), 'Kdrama Database '!$A$3:$A$1010, ""))} -> Black out, Go back couple, Hi bye, mama!, Queen for seven days , The heavenly idol
A127: Go Joon-Hee | C127: {=TEXTJOIN(", ", TRUE, IF(ISNUMBER(SEARCH(A127, 'Kdrama Database '!$G$3:$G$1010)), 'Kdrama Database '!$A$3:$A$1010, ""))} -> She was pretty
A128: Go Kyung-Pyo | C128: {=TEXTJOIN(", ", TRUE, IF(ISNUMBER(SEARCH(A128, 'Kdrama Database '!$G$3:$G$1010)), 'Kdrama Database '!$A$3:$A$1010, ""))} -> Chicago typewriter , Connect , Cross, D.P 2, Frankly speaking, Private lives, Reply 1988, Strongest deliveryman, Undercover miss hong
A129: Go Min-Si | C129: {=TEXTJOIN(", ", TRUE, IF(ISNUMBER(SEARCH(A129, 'Kdrama Database '!$G$3:$G$1010)), 'Kdrama Database '!$A$3:$A$1010, ""))} -> Jirisan, Love Alarm 1, Love Alarm 2, Sweet home 1, Sweet home 2, Sweet home 3, Tastefully yours, The frog, The smile has left your eyes, Youth of may
A130: Go Soo | C130: {=TEXTJOIN(", ", TRUE, IF(ISNUMBER(SEARCH(A130, 'Kdrama Database '!$G$3:$G$1010)), 'Kdrama Database '!$A$3:$A$1010, ""))} -> Missing: the other side, Missing: the other side 2, Money game, Witch's love
A131: Go Soo-Hee | C131: {=TEXTJOIN(", ", TRUE, IF(ISNUMBER(SEARCH(A131, 'Kdrama Database '!$G$3:$G$1010)), 'Kdrama Database '!$A$3:$A$1010, ""))} -> Witch's love
A132: Go Won-Hee | C132: {=TEXTJOIN(", ", TRUE, IF(ISNUMBER(SEARCH(A132, 'Kdrama Database '!$G$3:$G$1010)), 'Kdrama Database '!$A$3:$A$1010, ""))} -> King the land, Love to hate you, Strongest deliveryman, Welcome to waikiki 1
... A134: Go Youn-Jung | C134: {=TEXTJOIN(", ", TRUE, IF(ISNUMBER(SEARCH(A134, 'Kdrama Database '!$G$3:$G$1010)), 'Kdrama Database '!$A$3:$A$1010, ""))} -> Alchemy of souls 2, Can this love be translated?, Death's game, He is psychometric, Law school, Moving , Moving 2, Resident playbook, Sweet home 1, We are all trying here
A135: Gong Hyo-Jin | B135: https://pin.it/133xRgun5 | C135: {=TEXTJOIN(", ", TRUE, IF(ISNUMBER(SEARCH(A135, 'Kdrama Database '!$G$3:$G$1010)), 'Kdrama Database '!$A$3:$A$1010, ""))} -> A bona fide killer , When the camellia blooms, When the stars gossip
A136: Gong Min-Jung | B136: https://pin.it/3frsHZcI0 | C136: {=TEXTJOIN(", ", TRUE, IF(ISNUMBER(SEARCH(A136, 'Kdrama Database '!$G$3:$G$1010)), 'Kdrama Database '!$A$3:$A$1010, ""))} -> Boyfriend on demand, Hometown cha cha cha, Love: track, Marry my husband, Please don't date him, Sorry not Sorry
A137: Gong Myung | B137: https://pin.it/3dUftlzdX | C137: {=TEXTJOIN(", ", TRUE, IF(ISNUMBER(SEARCH(A137, 'Kdrama Database '!$G$3:$G$1010)), 'Kdrama Database '!$A$3:$A$1010, ""))} -> Be melodramatic, Filing for love, Lovers of the red sky, Mercy for none, Second shot at love, The bride of habaek, Way back love
A138: Gong Seung-Yeon | B138: https://pin.it/1RXfPzUJ1 | C138: {=TEXTJOIN(", ", TRUE, IF(ISNUMBER(SEARCH(A138, 'Kdrama Database '!$G$3:$G$1010)), 'Kdrama Database '!$A$3:$A$1010, ""))} -> Are you human too?, Bulgasal: immortal souls , Karma, My lovely journey, My lovely journey 2, My shy boss, Perfect crown, Six flying dragon , The first responders 1, The first responders 2
A139: Kong Seong-Ha | B139: https://share.google/5uSFFP4jeQgLMXMrl | C139: {=TEXTJOIN(", ", TRUE, IF(ISNUMBER(SEARCH(A139, 'Kdrama Database '!$G$3:$G$1010)), 'Kdrama Database '!$A$3:$A$1010, ""))} -> Doctor slump, Siren's kiss, Through the darkness
A140: Gong Yoo | B140: https://pin.it/qBYfk1eP9 | C140: {=TEXTJOIN(", ", TRUE, IF(ISNUMBER(SEARCH(A140, 'Kdrama Database '!$G$3:$G$1010)), 'Kdrama Database '!$A$3:$A$1010, ""))} -> Goblin, The silent sea , The trunk
A141: Goo Doo-Shim | B141: https://share.google/1jhCnnVHwLUrraqB3 | C141: {=TEXTJOIN(", ", TRUE, IF(ISNUMBER(SEARCH(A141, 'Kdrama Database '!$G$3:$G$1010)), 'Kdrama Database '!$A$3:$A$1010, ""))} -> Our blues, The atypical family
A142: Ha Ji-Won | C142: {=TEXTJOIN(", ", TRUE, IF(ISNUMBER(SEARCH(A142, 'Kdrama Database '!$G$3:$G$1010)), 'Kdrama Database '!$A$3:$A$1010, ""))} -> Chocolate, Climax, Empress ki
A143: Ha Jun | C143: {=TEXTJOIN(", ", TRUE, IF(ISNUMBER(SEARCH(A143, 'Kdrama Database '!$G$3:$G$1010)), 'Kdrama Database '!$A$3:$A$1010, ""))} -> Bad prosecutor , Crazy love, Destined with you, Missing: the other side, Missing: the other side 2, Narco saints , Our universe, Radio romance
A144: Ha Jung-Woo | C144: {=TEXTJOIN(", ", TRUE, IF(ISNUMBER(SEARCH(A144, 'Kdrama Database '!$G$3:$G$1010)), 'Kdrama Database '!$A$3:$A$1010, ""))} -> Narco saints
A145: Ha Seok-Jin | C145: {=TEXTJOIN(", ", TRUE, IF(ISNUMBER(SEARCH(A145, 'Kdrama Database '!$G$3:$G$1010)), 'Kdrama Database '!$A$3:$A$1010, ""))} -> Blind , D-day, To my beloved thief
A146: Ha Yoon-Kyung | C146: {=TEXTJOIN(", ", TRUE, IF(ISNUMBER(SEARCH(A146, 'Kdrama Database '!$G$3:$G$1010)), 'Kdrama Database '!$A$3:$A$1010, ""))} -> Extraordinary attorney woo, Gangnam B-side, See you in my 19th life, The apartment job, Undercover miss hong
A147: Ha Young | C147: {=TEXTJOIN(", ", TRUE, IF(ISNUMBER(SEARCH(A147, 'Kdrama Database '!$G$3:$G$1010)), 'Kdrama Database '!$A$3:$A$1010, ""))} -> Boyfriend on demand, Doona!, Face me, Let me be your Knight, Our sticky love , Teach you a lesson, The trauma code: heroes on call
A148: Ha Yu-Jun | C148: {=TEXTJOIN(", ", TRUE, IF(ISNUMBER(SEARCH(A148, 'Kdrama Database '!$G$3:$G$1010)), 'Kdrama Database '!$A$3:$A$1010, ""))} -> Spring of youth
A149: Ha Yul-Ri | C149: {=TEXTJOIN(", ", TRUE, IF(ISNUMBER(SEARCH(A149, 'Kdrama Database '!$G$3:$G$1010)), 'Kdrama Database '!$A$3:$A$1010, ""))} -> A bona fide killer , Pyramid game, Tale of lady ok, The red sleeve
A150: Han Chae-Ah | C150: {=TEXTJOIN(", ", TRUE, IF(ISNUMBER(SEARCH(A150, 'Kdrama Database '!$G$3:$G$1010)), 'Kdrama Database '!$A$3:$A$1010, ""))} -> Bridal mask
A151: Han Da-Gam | C151: {=TEXTJOIN(", ", TRUE, IF(ISNUMBER(SEARCH(A151, 'Kdrama Database '!$G$3:$G$1010)), 'Kdrama Database '!$A$3:$A$1010, ""))} -> Golden cross, Let me introduce her
A152: Han Ga-In | C152: {=TEXTJOIN(", ", TRUE, IF(ISNUMBER(SEARCH(A152, 'Kdrama Database '!$G$3:$G$1010)), 'Kdrama Database '!$A$3:$A$1010, ""))} -> Moon embracing: the sun
A153: Han Hyo-Joo | C153: {=TEXTJOIN(", ", TRUE, IF(ISNUMBER(SEARCH(A153, 'Kdrama Database '!$G$3:$G$1010)), 'Kdrama Database '!$A$3:$A$1010, ""))} -> Blood free, Happiness, In your radiant season, Moving , Moving 2, W-two worlds
... A158: Han Seung-Yeon | C158: {=TEXTJOIN(", ", TRUE, IF(ISNUMBER(SEARCH(A158, 'Kdrama Database '!$G$3:$G$1010)), 'Kdrama Database '!$A$3:$A$1010, ""))} -> Her lovely heels , The Scandal of Chunhwa
A159: Han So-Hee | B159: https://pin.it/1VB8XsQQF | C159: {=TEXTJOIN(", ", TRUE, IF(ISNUMBER(SEARCH(A159, 'Kdrama Database '!$G$3:$G$1010)), 'Kdrama Database '!$A$3:$A$1010, ""))} -> 100 days my prince , Abyss, Gyeongseong creature 1, Gyeongseong creature 2, Money flower, My name, Nevertheless, Soundtrack #1, The world of the married
A160: Han Suk-Kyu | B160: https://pin.it/7woePE68n | C160: {=TEXTJOIN(", ", TRUE, IF(ISNUMBER(SEARCH(A160, 'Kdrama Database '!$G$3:$G$1010)), 'Kdrama Database '!$A$3:$A$1010, ""))} -> Doubt, Dr. Romantic, Dr. Romantic 2, Dr. Romantic 3, Recipe for farewell, Tree with deep roots , Watcher
A161: Han Sun-Hwa | B161: https://pin.it/31IUSBJet | C161: {=TEXTJOIN(", ", TRUE, IF(ISNUMBER(SEARCH(A161, 'Kdrama Database '!$G$3:$G$1010)), 'Kdrama Database '!$A$3:$A$1010, ""))} -> Backstreet rookie, My sweet mobster, School (2017), We are all trying here, Work later, drink now, Work later, drink now 2
A162: Han Ye-Ji | B162: https://pin.it/7GJePPhpR | C162: {=TEXTJOIN(", ", TRUE, IF(ISNUMBER(SEARCH(A162, 'Kdrama Database '!$G$3:$G$1010)), 'Kdrama Database '!$A$3:$A$1010, ""))} -> User not found
A163: Han Ye-Ri | B163: https://pin.it/56xZ80Omy | C163: {=TEXTJOIN(", ", TRUE, IF(ISNUMBER(SEARCH(A163, 'Kdrama Database '!$G$3:$G$1010)), 'Kdrama Database '!$A$3:$A$1010, ""))} -> Doubt
A164: Heo Joon-Ho | B164: https://share.google/oNlZEuqudQnY0WkTD | C164: {=TEXTJOIN(", ", TRUE, IF(ISNUMBER(SEARCH(A164, 'Kdrama Database '!$G$3:$G$1010)), 'Kdrama Database '!$A$3:$A$1010, ""))} -> A beautiful mind , Bloodhounds, Buried hearts, Come and hug me, Designated survivors: 60 days , Kingdom , Kingdom 2, Mercy for none, Missing: the other side, Missing: the other side 2, Notes from the last row, Snowdrop, The emperor: owner of the mask, Undercover , Why her
A165: Heo Nam-Jun | B165: https://pin.it/5W2PZCafy | C165: {=TEXTJOIN(", ", TRUE, IF(ISNUMBER(SEARCH(A165, 'Kdrama Database '!$G$3:$G$1010)), 'Kdrama Database '!$A$3:$A$1010, ""))} -> A hundred memories, My royal nemesis, Snowdrop, Sweet home 2, Sweet home 3, When the phone rings, When the stars gossip
A166: Heo Sung-Tae | C166: {=TEXTJOIN(", ", TRUE, IF(ISNUMBER(SEARCH(A166, 'Kdrama Database '!$G$3:$G$1010)), 'Kdrama Database '!$A$3:$A$1010, ""))} -> Adamas, Behind every star, Beyond evil , Crash , Cross, Fifties professionals, Good boy, Insider, Our sticky love , Squid game, The silent sea , Watcher
A167: Heo Yool | C167: {=TEXTJOIN(", ", TRUE, IF(ISNUMBER(SEARCH(A167, 'Kdrama Database '!$G$3:$G$1010)), 'Kdrama Database '!$A$3:$A$1010, ""))} -> Mother
A168: Lee Ha-Nee | C168: {=TEXTJOIN(", ", TRUE, IF(ISNUMBER(SEARCH(A168, 'Kdrama Database '!$G$3:$G$1010)), 'Kdrama Database '!$A$3:$A$1010, ""))} -> Aema, Knight flower, The fiery priest , The fiery priest 2
A169: Hong Hwa-Yeon | C169: {=TEXTJOIN(", ", TRUE, IF(ISNUMBER(SEARCH(A169, 'Kdrama Database '!$G$3:$G$1010)), 'Kdrama Database '!$A$3:$A$1010, ""))} -> Buried hearts, Filing for love, I am a running mate, Tastefully yours
A170: Hong Jong-Hyun | C170: {=TEXTJOIN(", ", TRUE, IF(ISNUMBER(SEARCH(A170, 'Kdrama Database '!$G$3:$G$1010)), 'Kdrama Database '!$A$3:$A$1010, ""))} -> Dear x, Her lovely heels , Moon lovers: scarlet heart, Positively yours, Stock Struck, The king in love, What comes after love
A171: Hong Kyung | C171: {=TEXTJOIN(", ", TRUE, IF(ISNUMBER(SEARCH(A171, 'Kdrama Database '!$G$3:$G$1010)), 'Kdrama Database '!$A$3:$A$1010, ""))} -> Concrete market , D.P, Revenant , Weak hero class 1
A172: Hong Min-Gi | C172: {=TEXTJOIN(", ", TRUE, IF(ISNUMBER(SEARCH(A172, 'Kdrama Database '!$G$3:$G$1010)), 'Kdrama Database '!$A$3:$A$1010, ""))} -> Crushology 101, Doctor on the edge, Love your enemy, Study group, Study group 2, To my beloved thief
A173: Hong Seung-Hee | C173: {=TEXTJOIN(", ", TRUE, IF(ISNUMBER(SEARCH(A173, 'Kdrama Database '!$G$3:$G$1010)), 'Kdrama Database '!$A$3:$A$1010, ""))} -> Move to heaven, To the moon
A174: Hong Soo-Hyun | C174: {=TEXTJOIN(", ", TRUE, IF(ISNUMBER(SEARCH(A174, 'Kdrama Database '!$G$3:$G$1010)), 'Kdrama Database '!$A$3:$A$1010, ""))} -> Mad dog, My lovely journey
A175: Hong Su-Zu | C175: {=TEXTJOIN(", ", TRUE, IF(ISNUMBER(SEARCH(A175, 'Kdrama Database '!$G$3:$G$1010)), 'Kdrama Database '!$A$3:$A$1010, ""))} -> Moon river, Sweet home 3, The impossible heir
A176: Hong Ye-Ji | C176: {=TEXTJOIN(", ", TRUE, IF(ISNUMBER(SEARCH(A176, 'Kdrama Database '!$G$3:$G$1010)), 'Kdrama Database '!$A$3:$A$1010, ""))} -> Missing crown prince
A177: Hwak Shi-Yang | C177: {=TEXTJOIN(", ", TRUE, IF(ISNUMBER(SEARCH(A177, 'Kdrama Database '!$G$3:$G$1010)), 'Kdrama Database '!$A$3:$A$1010, ""))} -> My dearest nemesis
... A189: Hyun Bin | C189: {=TEXTJOIN(", ", TRUE, IF(ISNUMBER(SEARCH(A189, 'Kdrama Database '!$G$3:$G$1010)), 'Kdrama Database '!$A$3:$A$1010, ""))} -> Crash landing on you, Made in Korea, Made in korea 2, Memories of the alhambra
A190: Hyun Bong-Sik | B190: https://share.google/JQvLbi0sr0hV6qKvE | C190: {=TEXTJOIN(", ", TRUE, IF(ISNUMBER(SEARCH(A190, 'Kdrama Database '!$G$3:$G$1010)), 'Kdrama Database '!$A$3:$A$1010, ""))} -> A killer paradox, Aema, D.P, Gangnam B-side, Mousetrap , Narco saints , Nine puzzles , Sweet home 2, Sweet home 3, The bequeathed, The veil
A191: Hyun Woo | C191: {=TEXTJOIN(", ", TRUE, IF(ISNUMBER(SEARCH(A191, 'Kdrama Database '!$G$3:$G$1010)), 'Kdrama Database '!$A$3:$A$1010, ""))} -> If wishes could kill, Witch's love
A192: Hyun Woo-Seok | C192: {=TEXTJOIN(", ", TRUE, IF(ISNUMBER(SEARCH(A192, 'Kdrama Database '!$G$3:$G$1010)), 'Kdrama Database '!$A$3:$A$1010, ""))} -> If wishes could kill
A193: Hyunri | C193: {=TEXTJOIN(", ", TRUE, IF(ISNUMBER(SEARCH(A193, 'Kdrama Database '!$G$3:$G$1010)), 'Kdrama Database '!$A$3:$A$1010, ""))} -> A shop for killers 2
A194: Im Ji-Yeon | C194: {=TEXTJOIN(", ", TRUE, IF(ISNUMBER(SEARCH(A194, 'Kdrama Database '!$G$3:$G$1010)), 'Kdrama Database '!$A$3:$A$1010, ""))} -> High Society, Lies hidden in my garden , My royal nemesis, Tale of lady ok, The glory, The killing vote
A195: Lim Ju-Hwan | C195: {=TEXTJOIN(", ", TRUE, IF(ISNUMBER(SEARCH(A195, 'Kdrama Database '!$G$3:$G$1010)), 'Kdrama Database '!$A$3:$A$1010, ""))} -> Different dreams , Oh my ghost, The bride of habaek, Uncontrollably fond
A196: Im Se-Mi | C196: {=TEXTJOIN(", ", TRUE, IF(ISNUMBER(SEARCH(A196, 'Kdrama Database '!$G$3:$G$1010)), 'Kdrama Database '!$A$3:$A$1010, ""))} -> Duty after school: part 1, My dearest nemesis , My secret terrius , Shopaholic louis, The winning try, The worst of evil, True beauty, When the weather is fine, Wonderful world
A197: Im Seul-Ong | C197: {=TEXTJOIN(", ", TRUE, IF(ISNUMBER(SEARCH(A197, 'Kdrama Database '!$G$3:$G$1010)), 'Kdrama Database '!$A$3:$A$1010, ""))} -> Hogu's love
A198: Im Si-Wan | C198: {=TEXTJOIN(", ", TRUE, IF(ISNUMBER(SEARCH(A198, 'Kdrama Database '!$G$3:$G$1010)), 'Kdrama Database '!$A$3:$A$1010, ""))} -> Boyhood, Boyhood 2, Misaeng: incomplete life, Run on, Squid game 2, Squid game 3, Strangers from hell, Summer Strike, The king in love
A199: Im Soo-Hyang | C199: {=TEXTJOIN(", ", TRUE, IF(ISNUMBER(SEARCH(A199, 'Kdrama Database '!$G$3:$G$1010)), 'Kdrama Database '!$A$3:$A$1010, ""))} -> Doctor lawyer , Kokdu: season of deity , My ID is gangnam beauty
A200: Im Soo-Jung | C200: {=TEXTJOIN(", ", TRUE, IF(ISNUMBER(SEARCH(A200, 'Kdrama Database '!$G$3:$G$1010)), 'Kdrama Database '!$A$3:$A$1010, ""))} -> Chicago typewriter , Melancholia, Search: www
A201: Im Sung-Jae | C201: {=TEXTJOIN(", ", TRUE, IF(ISNUMBER(SEARCH(A201, 'Kdrama Database '!$G$3:$G$1010)), 'Kdrama Database '!$A$3:$A$1010, ""))} -> Hellbound 2, Law and the city, Love: track, Newtopia, The wonderfools, The worst of evil
A202: Lim Sung-Kyun | C202: {=TEXTJOIN(", ", TRUE, IF(ISNUMBER(SEARCH(A202, 'Kdrama Database '!$G$3:$G$1010)), 'Kdrama Database '!$A$3:$A$1010, ""))} -> Be my boyfriend, One: high school heroes, Shooting stars
... A210: Jang Dong-Yoon | C210: {=TEXTJOIN(", ", TRUE, IF(ISNUMBER(SEARCH(A210, 'Kdrama Database '!$G$3:$G$1010)), 'Kdrama Database '!$A$3:$A$1010, ""))} -> A poem a day, Daily dose of sunshine, Just dance, Like flowers in sand, My man is cupid, Oasis, Queen mantis, School (2017), Search, The tale of nokdu
A211: Jang Gwang | B211: https://pin.it/443wkrwjB | C211: {=TEXTJOIN(", ", TRUE, IF(ISNUMBER(SEARCH(A211, 'Kdrama Database '!$G$3:$G$1010)), 'Kdrama Database '!$A$3:$A$1010, ""))} -> A korean Odyssey , Connect , Cross, Stock Struck, The crowned clown, The husband
A212: Jang Gyu-Ri | B212: https://pin.it/7dJ48hS18 | C212: {=TEXTJOIN(", ", TRUE, IF(ISNUMBER(SEARCH(A212, 'Kdrama Database '!$G$3:$G$1010)), 'Kdrama Database '!$A$3:$A$1010, ""))} -> Cheer up, Four hands, two sonatas, When the phone rings
A213: Jang Hee-Jin | B213: https://share.google/gZcSTLxZAYwRtltyO | C213: {=TEXTJOIN(", ", TRUE, IF(ISNUMBER(SEARCH(A213, 'Kdrama Database '!$G$3:$G$1010)), 'Kdrama Database '!$A$3:$A$1010, ""))} -> Flower of evil, The red sleeve
A214: Jang Hee-Ryung | B214: https://pin.it/1RAK4MI23 | C214: {=TEXTJOIN(", ", TRUE, IF(ISNUMBER(SEARCH(A214, 'Kdrama Database '!$G$3:$G$1010)), 'Kdrama Database '!$A$3:$A$1010, ""))} -> Love refresh, Shooting stars, Sorry not Sorry, The boy next door , The witch
A215: Jang Hyuk | B215: https://pin.it/5rxhyNfTS | C215: {=TEXTJOIN(", ", TRUE, IF(ISNUMBER(SEARCH(A215, 'Kdrama Database '!$G$3:$G$1010)), 'Kdrama Database '!$A$3:$A$1010, ""))} -> A beautiful mind , Awaken, Fated to love you, Money flower, My bias, my boss, My country: the new age, Our sticky love , Taxi driver, Taxi driver 2, Taxi driver 3, Tell me what you saw, Tree with deep roots , Voice 1
A216: Jang Hyuk-Jin | C216: {=TEXTJOIN(", ", TRUE, IF(ISNUMBER(SEARCH(A216, 'Kdrama Database '!$G$3:$G$1010)), 'Kdrama Database '!$A$3:$A$1010, ""))} -> Awaken, My bias, my boss, Our sticky love , Taxi driver, Taxi driver 2, Taxi driver 3
A217: Jang Ki-Yong | C217: {=TEXTJOIN(", ", TRUE, IF(ISNUMBER(SEARCH(A217, 'Kdrama Database '!$G$3:$G$1010)), 'Kdrama Database '!$A$3:$A$1010, ""))} -> Come and hug me, Dynamite kiss, Go back couple, Kill it, My mister, My roommate is a gumiho, Now, we are breaking up, Search: www , The atypical family, The boy next door
A218: Jang Na-Ra | C218: {=TEXTJOIN(", ", TRUE, IF(ISNUMBER(SEARCH(A218, 'Kdrama Database '!$G$3:$G$1010)), 'Kdrama Database '!$A$3:$A$1010, ""))} -> Fated to love you, Go back couple, Good partner, Sell your haunted house
A219: Jang Sang-Hoon | C219: {=TEXTJOIN(", ", TRUE, IF(ISNUMBER(SEARCH(A219, 'Kdrama Database '!$G$3:$G$1010)), 'Kdrama Database '!$A$3:$A$1010, ""))} -> Team bulldog: off duty investigation
A220: Jang Seung-Jo | C220: {=TEXTJOIN(", ", TRUE, IF(ISNUMBER(SEARCH(A220, 'Kdrama Database '!$G$3:$G$1010)), 'Kdrama Database '!$A$3:$A$1010, ""))} -> As you stood by, Chocolate, Death's game, Encounter, Familiar wife, Money flower, My royal nemesis, Snowdrop, The good detective 1, The good detective 2
A221: Jang Sung-Yoon | C221: {=TEXTJOIN(", ", TRUE, IF(ISNUMBER(SEARCH(A221, 'Kdrama Database '!$G$3:$G$1010)), 'Kdrama Database '!$A$3:$A$1010, ""))} -> Bitch x rich
A222: Jang Yeo-Bin | C222: {=TEXTJOIN(", ", TRUE, IF(ISNUMBER(SEARCH(A222, 'Kdrama Database '!$G$3:$G$1010)), 'Kdrama Database '!$A$3:$A$1010, ""))} -> All that we loved
A223: Jeon Do-Yeon | C223: {=TEXTJOIN(", ", TRUE, IF(ISNUMBER(SEARCH(A223, 'Kdrama Database '!$G$3:$G$1010)), 'Kdrama Database '!$A$3:$A$1010, ""))} -> Crash course in romance, Lost , The price of confession
A224: Jeon Hye-Bin | C224: {=TEXTJOIN(", ", TRUE, IF(ISNUMBER(SEARCH(A224, 'Kdrama Database '!$G$3:$G$1010)), 'Kdrama Database '!$A$3:$A$1010, ""))} -> Another miss oh, Beyond the bar
A225: Jeon Hye-Jin | C225: {=TEXTJOIN(", ", TRUE, IF(ISNUMBER(SEARCH(A225, 'Kdrama Database '!$G$3:$G$1010)), 'Kdrama Database '!$A$3:$A$1010, ""))} -> Love: track, Misty, Reborn Rookie , Search: www , Soundtrack #2, Stranger 2
A226: Jeon Jin-Seo | C226: {=TEXTJOIN(", ", TRUE, IF(ISNUMBER(SEARCH(A226, 'Kdrama Database '!$G$3:$G$1010)), 'Kdrama Database '!$A$3:$A$1010, ""))} -> Begins ≠ Youth
A227: Jeon Jong-Seo | C227: {=TEXTJOIN(", ", TRUE, IF(ISNUMBER(SEARCH(A227, 'Kdrama Database '!$G$3:$G$1010)), 'Kdrama Database '!$A$3:$A$1010, ""))} -> Bargain , Money heist: Korea - Joint Economic Area - part 1, Queen woo, Wedding impossible
... A231: Jeon So-Young | C231: {=TEXTJOIN(", ", TRUE, IF(ISNUMBER(SEARCH(A231, 'Kdrama Database '!$G$3:$G$1010)), 'Kdrama Database '!$A$3:$A$1010, ""))} -> If wishes could kill, Kick kick kick kick, My youth, Study group 2
...

Sheet Kdrama Database 
A1: DRAMOIR · Drama Database
A2: Title | B2: type | C2: country | D2: Year | E2: Episodes | F2: Status | G2: Main role | H2: Genres | I2: Tropes | J2: Mood / Vibe Tags | K2: Global Rating (/10) | L2: Poster URL | M2: Banner URL | N2: Synopsis | O2: Curated Collections
A3: 100 days my prince | B3: series | C3: Korea | D3: 2018 | E3: 16 | F3: Completed | G3: Do Kyung-Soo, Nam Ji-Hyun, Kim Seon-Ho, Jo Sung-Ha, Han So-Hee, Kim Jae-Yeong | H3: romcom, Drama, historical | I3: Joseon era, contract relationship, fake marriage, Memory Loss / amnesia, Palace intrigue, secret identity, childhood connection / first meeting, fated / destined love, grumpy x sunshine, cold / tsundere ML, found family, secret past revealed, Co-habitation / living together, chemistry overload, hate to tolerance to love | J3: feel-good, comfort drama, chaotic fun, episode 1 hook, aesthetically beautiful, emotional rollercoaster, OST is everything | K3: 7.8 | L3: https://pin.it/1JccWz0Zo | M3: https://pin.it/544vsLYL8 | N3: Lee Yul is an uncompromising, perfectionist Crown Prince who survives an assassination attempt but loses his memory, waking up as a clueless commoner named Won-deuk. Meanwhile, Hong-shim is an intelligent, fiercely independent woman forced into a royal decree to marry immediately or face punishment. The two end up in a chaotic contract marriage, with the spoiled prince struggling to adapt to peasant life while his hidden past catches up to him.
A4: 18 again | B4: series | C4: Korea | D4: 2020 | E4: 16 | F4: Completed | G4: Lee Do-Hyun, Kim Ha-Neul, Yoon Sang-Hyun, Roh Jeong-Eui, Ryeoun, Wi Ha-Joon | H4: romcom, Drama, fantasy, family, school | I4: second chance romance, healing romance, single parent, grumpy x sunshine, protective ML, green flag ML, career-driven FL, hidden true self, family dynamics, adult returning to highschool, highschool setting, character growth, love triangle | J4: healing & therapeutic, cry fest, emotional rollercoaster | K4: 8.6 | L4: https://pin.it/5ClG7w5uB | M4: https://pin.it/4MFsVvX5c | N4: On the brink of divorce and suffering through a dead-end career, 37-year-old Hong Dae-young suddenly morphs back into his peak 18-year-old body while retaining his adult mind. Under a fake identity, he attends his teenage twins' high school, getting a front-row seat to the struggles of the family he unintentionally neglected.
A5: 365: repeat the year | B5: series | C5: Korea | D5: 2020 | E5: 24 | F5: Completed | G5: Lee Jun-Hyuk, Nam Ji-Hyun, Kim Jee-Soo, Lee Sung-Wook, Ahn Seung-Gyun, Yang Dong-Geun, Ryeoun | H5: thriller, mystery, crime, psychological, sci-fi | I5: time travel, parallel world crossing, murder mystery, serial killer hunt, investigation, cat-and-mouse chase, betrayal, secret past revealed, no romance | J5: episode 1 hook, plot twist heavy, dark & heavy | K5: 7.8 | L5: https://pin.it/CWtoIKDlN | M5: https://pin.it/6ACjj7dqP | N5: Ji Hyung-ju is a dedicated homicide detective struggling with the tragic murder of his partner, and Shin Ga-hyun is a successful webtoon artist paralyzed by a sudden hit-and-run accident. They are invited by a mysterious psychiatrist to participate in a "reset," traveling back exactly one year in time to rewrite their fates. However, when the participants begin dying one by one in a series of highly suspicious, calculated murders, they must team up to stop the killer.
A6: 7 first kisses | B6: series | C6: Korea | D6: 2016 | E6: 8 | F6: Completed | G6: Lee Cho-Hee, Choi Ji-Woo, Lee Joon-Gi, Park Hae-Jin, Ji Chang-Wook, Kai, Ok Taec-Yeon, Lee Jong-Suk, Lee Min-Ho | H6: fantasy, comedy, romance | I6: supernatural abilities / powers, magical element, curse / spell, CEO x Employee, Celebrity x Normal Citizen, secret identity, hidden true self, workplace romance, forced proximity, fake dating, clumsy FL, multiple leads, chemistry overload | J6: chaotic fun, easy watch, feel-good | K6: 6.1 | L6: https://pin.it/66cSrnzw9 | M6: https://pin.it/4MCQ0AzeD | N6: Min Soo-jin is a lonely, twenty-five-year-old Duty-Free shop employee who has never had a romantic relationship or experienced a single kiss in her entire life. Her mundane routine turns completely surreal when she helps a mysterious, supernatural goddess who rewards her by granting an extraordinary magical gift: Soo-jin is given the chance to choose between seven distinct, hyper-glorious dream partners across different fantasy scenarios, including a billionaire CEO, a secret agent, and a K-pop superstar.
A7: A beautiful mind | B7: series | C7: Korea | D7: 2016 | E7: 14 | F7: Completed | G7: Jang Hyuk, Park So-Dam, Yoon Hyun-Min, Park Se-Young, Heo Joon-Ho, Oh Jung-Se | H7: medical, mystery, psychological, romance, melodrama | I7: slow burn romance, workplace setting, medical / hospital setting, investigation, murder mystery, cold / tsundere ML, career-driven FL, psychopathic villain, character growth, corruption / power abuse, older ML (oppa), age gap romance, character driven | J7: "slow starter, worth it", underrated gem, dark & heavy | K7: 7.7 | L7: https://pin.it/1RogV7Gkw | M7: https://pin.it/19zQwEfXv | N7: A genius neurosurgeon who is completely unable to feel empathy due to a frontal lobe injury finds himself at the center of a series of mysterious hospital patient deaths. When a stubborn rookie traffic cop begins investigating, she forces him to navigate human emotions for the first time to track down the killer.
A8: A bona fide killer | B8: series | C8: Korea | D8: 2026 | E8: 14 | F8: Completed | G8: Gong Hyo-Jin, Jung joon-Won, Lee Sang-Yi, Shin Hyun-Soo, Sung Dong-Il, Seo Jung-Yeon, Moo Jin-Sung, Ha Yul-Ri, Choi Woo-Sung, Lee Eun-Saem | H8: action, thriller, Drama, crime, comedy | I8: investigation, dark justice, secret identity, hidden true self, smothering mother-in-law, tragic backstory, coming-of-age journey, He-Falls-First, unrequited love, mature romance, Golden Retriever ML, alpha / strong FL, double life, Heroic Save, family dynamics, workplace team bond, murder mystery, secret past revealed | J8: fast-paced, dark & heavy, Intense action, emotional rollercoaster | K8: 7.3 | L8: https://pin.it/1IhU1L6tv | M8: https://pin.it/4aV7deqaL | N8: Yoo Bo-na appears to be an ordinary working mother raising her young daughter with her reporter husband, but she secretly leads a double life as Kingfisher, a legendary assassin who eliminates criminals who escape the law. After returning from maternity leave, she must balance deadly assignments with family life—especially when her husband is tasked with investigating the very assassin whose identity she has sworn to protect.
A9: A business proposal | B9: series | C9: Korea | D9: 2022 | E9: 12 | F9: Completed | G9: Ahn Hyo-Seop, Kim Se-Jeong, Kim Min-Gue, Seol In-Ah | H9: romcom, family | I9: He-Falls-First, fake dating, contract relationship, secret dating, workplace romance, Rich x Poor, CEO x Employee, protective ML, yearning / lovesick ML, career-driven FL, bromance, sisterhood, workplace team bond, mistaken identity, workplace setting, webtoon adaptation, top tier kiss, Calm x Chaotic, chemistry overload | J9: feel-good, easy watch, episode 1 hook, chaotic fun, OST is everything, rewatchable | K9: 8.1 | L9: https://pin.it/OODVjjFRw | M9: https://pin.it/5HrKBENcS | N9: When Shin Ha-ri agrees to disguise herself as a glamorous femme fatale to ruin a blind date on behalf of her wealthy best friend, she expects a quick and chaotic exit. Instead, she finds herself sitting across from Kang Tae-moo—the brilliant, workaholic, and completely ruthless new CEO of her own company, who decides to marry her just to stop his grandfather's nagging.
A10: A good day to be a dog | B10: series | C10: Korea | D10: 2023 | E10: 14 | F10: Completed | G10: Cha Eun-Woo, Park Gyu-Young, Lee Hyun-Woo, Yoon Hyun-Soo | H10: romcom, fantasy, school, Drama | I10: He-Falls-First, forced proximity, healing romance, introvert x extrovert , protective ML, green flag ML, curse / spell, past-life connection, Teacher x Student, workplace setting, highschool setting, supernatural abilities / powers, webtoon adaptation, top tier kiss | J10: feel-good, comfort drama, healing & therapeutic, chaotic fun | K10: 8.2 | L10: https://pin.it/2jvwZuHWv | M10: https://pin.it/37bG9EqEN | N10: High school teacher Han Hae-na harbors a bizarre generational family curse: if she kisses a man, she transforms into a dog at midnight for six hours until she can kiss the same man again in her dog form. After mistakenly kissing her distant colleague, Jin Seo-won, she discovers that breaking her curse will be nearly impossible because he has a debilitating, secret phobia of dogs.
A11: A hundred memories | B11: series | C11: Korea | D11: 2025 | E11: 12 | F11: Completed | G11: Kim Da-Mi, Shin Ye-Eun, Heo Nam-Jun, Kim Jung-Hyun, Lee Won-Jung, Jeon Sung-Woo | H11: romance, Drama, historical, slice-of-life, youth | I11: first love, unresolved feelings , tragic separation, Bittersweet / Realistic romance, sisterhood, coming-of-age journey, grief & loss, adult life struggles, THE confrontation, 1980s setting, retro / period setting, family dynamics, secret past revealed, tragic backstory | J11: emotional rollercoaster, aesthetically beautiful, underrated gem, disappointing ending | K11: 7.6 | L11: https://pin.it/5wAf0PvFB | M11: https://pin.it/4YdVqNEOH | N11: Set in 1980s South Korea, Go Young-rye works as a bus hostess on route 100 while dreaming of going to university. Her life changes when charismatic newcomer Seo Jong-hee joins the bus company, and the two women become close friends. Their friendship becomes complicated when both become connected to Han Jae-pil, leading to first love, rivalry, painful separation, and the struggles of growing into adulthood.
A12: A killer paradox | B12: series | C12: Korea | D12: 2024 | E12: 8 | F12: Completed | G12: Choi Woo-Shik, Son Suk-Ku, Lee Hee-Joon, Hyun Bong-Sik | H12: crime, thriller, mystery, psychological | I12: serial killer hunt, accidental murder / witness, framed for a crime, investigation, mind games / psychological warfare, partners in crime, life lessons, secret identity, dark justice, no romance, dark comedy | J12: binge-worthy, episode 1 hook, plot twist heavy, dark & heavy | K12: 7.1 | L12: https://pin.it/4ISd2MzKJ | M12: https://pin.it/7sOGkXJrR | N12: An ordinary, aimless college student accidentally murders a rude customer during his convenience store part-time job, sending him into a panic. However, he soon discovers that his victim was actually a horrific serial killer—and that he possesses a supernatural, latent ability to instinctively identify evil targets, kicking off a brutal cat-and-mouse game with a relentless police detective.
A13: A korean Odyssey | B13: series | C13: Korea | D13: 2017 | E13: 20 | F13: Completed | G13: Lee Seung-Gi, Cha Seung-Won, Oh Yeon-Seo, Lee Hong-Gi, Jang Gwang, Lee El | H13: romance, fantasy, comedy, horror | I13: Human x Supernatural Entity, supernatural abilities / powers, ghost / spirit, contract relationship, forced proximity, fated / destined love, epic romance, Star-Crossed Lovers, tragic separation, yearning / lovesick ML, second couple syndrome, chemistry overload, hate to tolerance to love | J13: chaotic fun, emotional rollercoaster, plot twist heavy, OST is everything, disappointing ending | K13: 7.9 | L13: https://pin.it/4hi9WoLs4 | M13: https://pin.it/6WvfwPnEs | N13: Son Oh-gong is an extraordinarily powerful, arrogant, and mischievous mythical monkey god who was banished to the human world with his powers sealed. He crosses paths with Jin Seon-mi, a successful real estate CEO who possesses the supernatural ability to see ghosts and demons. Bound by a magical bracelet called the Geumganggo, Oh-gong is forced to become her ultimate, fiercely protective guardian against dark spiritual forces, igniting a dangerous romance.
A14: A love so beautiful | B14: series | C14: Korea | D14: 2020 | E14: 24 | F14: Completed | G14: Kim Yo-Han, So Joo-Yeon, Yeo Hoi-Hyun, Jo Hye-Joo, Jung Jae-Oh | H14: romcom, youth, school, slice-of-life | I14: friends to lovers, school romance, She-Falls-First, first love, second lead syndrome, introvert x extrovert , Calm x Chaotic, cold / tsundere ML, clumsy FL, naive / innocent FL, friends group, neighbours, coming-of-age journey, character growth, highschool setting | J14: comfort drama, feel-good, easy watch | K14: 7.2 | L14: https://pin.it/2ufu9xujc | M14: https://pin.it/4XHf7LevD | N14: A bright, overly cheerful high schooler harboring a massive, seventeen-year unrequited crush on her brilliant, emotionally cold next-door neighbor relentlessly confesses her feelings. The story tracks their close-knit friend group as they transition from clumsy teenagers into young adults facing real-world heartbreaks.
... A30: All of us are dead | B30: series | C30: Korea | D30: 2022 | E30: 12 | F30: Completed | G30: Park Ji-Hu, Yoon Chan-Young, Cho Yi-Hyun, Lomon, Yoo In-Soo, Lee Yoo-Mi, Lee Sang-Hee, Kim Byung-chul | H30: action, thriller, horror, sci-fi, school | I30: zombie / apocalypse, k-trauma, highschool setting, friends group, survival thriller, Heroic Save, grief & loss, betrayal, alpha / strong FL, protective ML, multiple leads, introvert x extrovert, chemistry overload | J30: binge-worthy, episode 1 hook, emotional rollercoaster, dark & heavy, plot twist heavy, gory & violent | K30: 7.6 | L30: https://pin.it/J1Pn0voSQ | M30: https://pin.it/4aRWXjfUE | N30: A regular high school becomes ground zero for a devastating zombie virus outbreak. With no food, no cell service, and no rescue coming from the outside world, a tight-knit squad of students must band together using classroom equipment to survive a bloody escape against their turned classmates.
A31: All of us are dead 2 | B31: series | C31: Korea | D31: 2027 | E31: 12 | F31: Upcoming | G31: Park Ji-Hu, Yoon Chan-Young, Cho Yi-Hyun, Lomon, Lee Min-Jae, Kim Si-Eun, Roh Jae-Won, Yoon Ga-I | H31: action, thriller, horror, sci-fi, school | I31: zombie / apocalypse, k-trauma, friends group, survival thriller, grief & loss, overcoming trauma, life lessons, alpha / strong FL, protective ML, multiple leads | J31: binge-worthy, emotional rollercoaster, dark & heavy, plot twist heavy, gory & violent | L31: https://pin.it/6m01pj1Jp | N31: After surviving the catastrophic zombie outbreak at Hyosan High, Nam On Jo is now a university student in Seoul, struggling to move on from the trauma and the friends she lost. But when a new wave of infection suddenly hits Seoul, she finds herself trapped in another deadly fight for survival — this time without the people she once depended on.
A32: All that we loved | B32: series | C32: Korea | D32: 2023 | E32: 8 | F32: Completed | G32: Oh Se-Hun, jang Yeo-Bin, Cho Jun-Young, Lee Seung-Joon, Jeon Yeong-In, Song Jae-Rim, Jung Eugene | H32: youth, romance, Drama | I32: school romance, highschool setting, bromance, childhood connection / first meeting, friends to lovers, first love, love triangle, second lead syndrome, friends group, hidden true self, coming-of-age journey, supernatural abilities / powers | J32: emotional rollercoaster, aesthetically beautiful, easy watch, cry fest, underrated gem | K32: 7.1 | L32: https://pin.it/4SBhBJfwT | M32: https://pin.it/2v25LAd3v | N32: High school best friends Go Yoo and Go Joon-hee are inseparable, but Joon-hee suffers from severe health issues that require a kidney transplant, which Go Yoo willingly donates. Following the surgery, Joon-hee experiences cellular memory syndrome—inheriting Go Yoo's habits and intense romantic feelings for Han So-yeon, a transfer student who harbors a secret.
A33: Angel's last mission: Love | B33: series | C33: Korea | D33: 2019 | E33: 16 | F33: Completed | G33: Shin Hye-Sun, Kim Myung-Soo, Lee Dong-Gun, Kim Bo-Mi, Do Ji-Won, Kim In-Kwok | H33: romcom, fantasy, Drama | I33: contract relationship, Co-habitation / living together, forced proximity, fated / destined love, forbidden love, tragic separation, grumpy x sunshine, Golden Retriever ML, alpha / strong FL, overcoming trauma, bodyguard duty, childhood connection / first meeting, Human x Supernatural Entity, supernatural abilities / powers, chemistry overload | J33: emotional rollercoaster, feel-good, underrated gem, OST is everything | K33: 7.7 | L33: https://pin.it/2atSSXwES | M33: https://pin.it/4qUikuhqG | N33: Dan is a carefree, mischievous angel who is about to be sent to the afterlife when he is given a crucial, final mission: he must find true love for Lee Yeon-seo, a cynical, cold-hearted ballerina who lost her sight and her dreams in a tragic accident. The mission turns chaotic when the angel falls in love with her himself.
A34: Anna | B34: series | C34: Korea | D34: 2022 | E34: 8 | F34: Completed | G34: Bae Suzy, Jung Eun-Chae, Kim Jun-Han, Park Ye-Young | H34: melodrama, thriller, psychological | I34: secret identity, alpha / strong FL, career-driven FL, psychopathic villain, mind games / psychological warfare, corruption / power abuse, inheritance battle, chaebol family drama, class divide conflict, empowerment, revenge, betrayal, tragic backstory, character driven | J34: plot twist heavy, aesthetically beautiful, binge-worthy | K34: 7.1 | L34: https://pin.it/TzALMzSNi | M34: https://pin.it/3noUJQ16q | N34: Lee Yu-mi is a brilliant but desperately poor woman working exhausting, low-wage jobs. Pushed to her absolute limit by the cruel class divide conflict of an elite family, she decides to steal her wealthy boss's identity, reinventing herself as a highly cultured professor named "Anna"—leading her into a tense, psychological web of lies.
A35: Another miss oh | B35: series | C35: Korea | D35: 2016 | E35: 18 | F35: Completed | G35: Eric Moon, Seo Hyun-Jin, Jeon Hye-Bin, Ye Ji-Won, Kim Ji-Seok | H35: romcom, Drama, fantasy | I35: forced proximity, secret dating, fated / destined love, second lead syndrome, love triangle, healing romance, workplace romance, cold / tsundere ML, clumsy FL, Calm x Chaotic, unnecessary misunderstanding, supernatural abilities / powers, mistaken identity, Co-habitation / living together, hate to tolerance to love | J35: emotional rollercoaster, classic, disappointing ending | K35: 7.7 | L35: https://pin.it/2hDOI6ZrQ | M35: https://pin.it/5aOzF1men | N35: A sound director who was left at the altar develops mysterious, vivid psychic visions of a woman he has never met. When he accidentally ruins the business of a woman named Oh Hae-young—unintentionally mistaking her for his beautiful ex-fiancée who shares the exact same name—their lives become inextricably tangled.
A36: Are you human too? | B36: series | C36: Korea | D36: 2018 | E36: 36 | F36: Completed | G36: Seo Kang-Joon, Gong Seung-Yeon, Kim Sung-ryung, Lee Jun-Hyuk, Park Hwan-Hee | H36: sci-fi, romance, mystery, Drama, action | I36: forced proximity, forbidden love, slow burn romance, protective ML, green flag ML, alpha / strong FL, corruption / power abuse, Heroic Save, bodyguard duty, tech-driven romance, secret identity, Human x Supernatural Entity, chaebol family drama | J36: plot twist heavy, easy watch, underrated gem | K36: 7.9 | L36: https://pin.it/7bPkTmNxF | M36: https://pin.it/72PBQeAIE | N36: When a wealthy chaebol heir falls into a sudden coma following a mysterious accident, his brilliant scientist mother creates a highly advanced, identical AI android named Nam Shin III to take his place. To protect his identity from greedy corporate predators, the completely green flag, empathetic android is assigned a fierce former MMA fighter as his bodyguard.
A37: Arthdal chronicles | B37: series | C37: Korea | D37: 2019 | E37: 18 | F37: Completed | G37: Song Joong-Ki, Jang Dong-Gun, Kim Ji-Won, Kim Ok-Bin, Park Hae-Joon, Park Byung-Eun | H37: historical, romance, fantasy, political, action | I37: fantasy world, Palace intrigue, epic romance, tragic separation, secret identity, Underdog vs. Elite, class divide conflict, alpha / strong FL, protective ML, multiple leads | J37: dark & heavy, emotional rollercoaster, underrated gem | K37: 8.2 | L37: https://pin.it/5gsulms2b | M37: https://pin.it/59AGeBr8L | N37: Set in the mythical, ancient land of Arth during the Bronze Age, Eun-seom is an outcast born with a cursed fate who fights tirelessly to rescue his peaceful Wahan tribe from brutal enslavement. He faces off against Ta-gon, a brilliant, terrifyingly ruthless military war hero who seeks to establish the land's first absolute monarchy through high-stakes political manipulation and tribal bloodshed.
A38: Arthdal chronicles 2 : the sword of aramun | B38: series | C38: Korea | D38: 2023 | E38: 12 | F38: Completed | G38: Lee Joon-Gi, Shin Se-Kyung, Jang Dong-Gun, Kim Ok-Bin, Park Hae-Joon, Park Byung-Eun | H38: historical, romance, fantasy, political, action | I38: fantasy world, Palace intrigue, tragic separation, secret identity, Underdog vs. Elite, class divide conflict, alpha / strong FL, protective ML, multiple leads | J38: dark & heavy, emotional rollercoaster | K38: 8.2 | L38: https://pin.it/51iOldwqq | M38: https://pin.it/5wnXLp2xr | N38: Set eight years after Ta-gon successfully ascended the throne as the inaugural king of Arthdal, the ancient, mythical land faces an monumental war for absolute control. Having spend nearly a decade quelling internal revolts to stand as an unassailable sovereign, Ta-gon must fight to conquer the massive Ago Union, which has successfully united under the fierce leadership of Eun-seom. As the armies clash for survival, the complex fates of legendary heroes, priests, and warriors intertwine to redefine power and prophecy.
A39: As you stood by | B39: series | C39: Korea | D39: 2025 | E39: 12 | F39: Completed | G39: Jeon So-Nee, Lee Yoo-Mi, Jang Seung-Jo, Lee Mu-Saeng, Lee Ho-Jung | H39: Drama, crime, thriller, psychological | I39: investigation, sisterhood, partners in crime, found family, overcoming trauma, grief & loss, mind games / psychological warfare, vigilante justice, betrayal, tragic backstory, Bittersweet / Realistic romance, toxic relationship, k-trauma | J39: plot twist heavy, dark & heavy, emotional rollercoaster, ending will destroy you | K39: 7.5 | L39: https://pin.it/99YinECwl | M39: https://pin.it/4N24zhYv5 | N39: When Hui-su becomes trapped in an abusive marriage, her childhood friend Eun-su, who grew up witnessing domestic violence herself, decides to help her escape. The two women make a desperate plan to murder Hui-su's violent husband, but what initially seems like a foolproof plan quickly goes wrong when an unexpected person from their past threatens to expose everything.
A40: At a distance, spring is green | B40: series | C40: Korea | D40: 2021 | E40: 12 | F40: Completed | G40: Park Ji-Hoon, Kang Min-Ah, Bae In-Hyuk, Kwon Eun-Bin, Woo Da-Vi, Na In-Woo | H40: slice-of-life, romance, Drama, youth, school | I40: friends to lovers, comfort romance, healing romance, grumpy x sunshine, bromance, friends group, coming-of-age journey, overcoming trauma, childhood trauma, school bullying, university / campus, academic pressure | J40: healing & therapeutic, comfort drama, underrated gem | K40: 7.8 | L40: https://pin.it/1FENUfVlj | M40: https://pin.it/3dDTSVf49 | N40: From the outside, wealthy university freshman Yeo Jun has a perfect life, but he secretly hides deep childhood trauma and a severe lack of genuine affection. He forms a complicated, highly unexpected bond with a cynical, fiercely independent third-year student who works multiple jobs to survive, navigating the real struggles of youth together.
A41: Avengers social club | B41: series | C41: Korea | D41: 2017 | E41: 12 | F41: Completed | G41: Lee Yo-Won, Ra Mi-Ran, Myung Se-Bin, Lee Jun-Young, Choi Byung-Mo, Jung Suk-Yong | H41: comedy, Drama, family, slice-of-life, school | I41: no romance, sisterhood, found family, neighborhood squad, adult life struggles, investigation, dark justice, corruption / power abuse, Underdog vs. Elite, empowerment, class divide conflict, revenge, Ajummas lead (middle-aged women), highschool setting | J41: comfort drama, feel-good, "slow starter, worth it" | K41: 7.9 | L41: https://pin.it/6KejcIGMM | M41: https://pin.it/1iMTu6nI1 | N41: Three women from vastly different socio-economic backgrounds—a sheltered chaebol heiress, a traditional market fish store owner, and a submissive housewife—discover they are all victims of betrayal and family domestic abuse. Alongside an underdog high school student, they form a secret, hilarious vigilante alliance to carry out non-violent revenge.
A42: Awaken | B42: series | C42: Korea | D42: 2020 | E42: 16 | F42: Completed | G42: Namgoong Min, Kim Seol-Hyun, Lee Chung-Ah, Yoon Sun-Woo, Jang Hyuk-Jin | H42: thriller, mystery, crime, sci-fi, psychological | I42: investigation, cat-and-mouse chase, murder mystery, psychopathic villain, dark justice, corruption / power abuse, supernatural abilities / powers, secret past revealed, tragic backstory, partners in crime, workplace team bond, alpha / strong FL, protective ML, childhood connection / first meeting | J42: plot twist heavy, dark & heavy, "slow starter, worth it", underrated gem | K42: 7.5 | L42: https://pin.it/6mMJQ5clz | M42: https://pin.it/I1xDpN7YV | N42: A chaotic but brilliant police task force leader and a sharp FBI criminal profiler investigate a terrifying string of modern "preview murders" that warn victims of their deaths beforehand. The dark trail leads them straight back to uncovering a horrific, classified government experiment that took place in a mysterious village twenty-eight years ago.
A43: Azure spring | B43: series | C43: Korea | D43: 2026 | E43: 6 | F43: Completed | G43: Kang Sang-Joon, Yeri, Ko Ju-Hee, Jung yeon-Min | H43: slice-of-life, youth, Drama | I43: unresolved feelings , comfort romance, village romance, Co-habitation / living together, forced proximity, introvert x extrovert , grumpy x sunshine, green flag ML, found family, healing journey, secret past revealed, small town / island setting | J43: aesthetically beautiful, comfort drama, easy watch, healing & therapeutic | K43: 6.5 | L43: https://pin.it/5QbE5qQ89 | M43: https://pin.it/2NOCkgzTm | N43: An anxious city job seeker reeling from a failed career path escapes to a quiet island village in Haenam-gun, where she crosses paths with a guarded local man paralyzed by a deep personal trauma. Seeking a clean slate, both decide to learn the rigorous traditional practice of freediving as haenyeo and haenam, letting the rhythm of the ocean slowly heal their buried emotional wounds.
... A76: Boyhood | B76: series | C76: Korea | D76: 2023 | E76: 10 | F76: Completed | G76: Im Si-Wan, Lee Sun-Bin, Lee Si-Woo, Kang Hye-Won | H76: comedy, action, thriller, youth, school | I76: no romance, secret identity, mistaken identity, school bullying, underdog squad, friends group, coming-of-age journey, highschool setting, 1980s setting, retro / period setting, family dynamics, street fights / hand-to-hand combat | J76: chaotic fun, feel-good, binge-worthy, underrated gem | K76: 7.9 | L76: https://pin.it/1keUpwqbk | M76: https://pin.it/7v5h0sOAp | N76: Jang Byeong-gu is a clumsy, weak, and chronically bullied high school student living in rural South Chungcheong Province in 1989. His miserable life takes an unbelievable turn when he transfers to a new agricultural school and is instantly mistaken for the "White Tiger of Asan"—a legendary, undefeated high school street fighter. Embracing his accidental secret identity, Byeong-gu steps into the spotlight as the school's top dog, leading to chaotic high school standoffs.
A77: Boyhood 2 | B77: series | C77: Korea | D77: 2026 | F77: Upcoming | G77: Im Si-Wan, Lee Sun-Bin | H77: comedy, action, thriller, youth, school | I77: highschool setting, school bullying, secret identity, 1980s setting, street fights / hand-to-hand combat, underdog squad, friends group, coming-of-age journey, character growth | J77: chaotic fun, feel-good | L77: https://pin.it/6jtnEr3Rm | N77: Picking up after the chaotic events of the 1989 school year, clumsy student Jang Byeong-gu finds his hard-won peace threatened when real heavy-hitting fighters and a new crop of transfer students arrive in South Chungcheong Province. Forced to defend his accidental legacy and protect his loyal underdog squad, Byeong-gu must navigate escalating high school rivalries, complex retro romance, and the challenges of entering adulthood.
A78: Branding in seongsu | B78: series | C78: Korea | D78: 2024 | E78: 24 | F78: Completed | G78: Kim Ji-Eun, Lomon, Yang Hye-Ji, Kim Ho-Young | H78: romance, fantasy, Drama | I78: enemies to lovers, forced proximity, workplace romance, CEO x Employee, grumpy x sunshine, alpha / strong FL, career-driven FL, soul swap, investigation, mind games / psychological warfare, workplace setting | J78: binge-worthy, plot twist heavy, chaotic fun | K78: 6.5 | L78: https://pin.it/3IXfNcBlj | M78: https://pin.it/W2nDaulyp | N78: A ruthless, workaholic marketing agency team leader and a completely unmotivated, warm-hearted intern find their souls swapped after an accidental, unexpected kiss. Trapped in each other's bodies, they are forced to co-manage high-stakes brand campaigns while searching for a way to reverse the switch.
A79: Brewing love | B79: series | C79: Korea | D79: 2024 | E79: 12 | F79: Completed | G79: Kim Se-Jeong, Lee Jong-Won, Shin Do-Hyun, Baek Sung-Chul | H79: romcom, Drama, slice-of-life | I79: hate to tolerance to love, He-Falls-First, slow burn romance, workplace romance, village romance, introvert x extrovert , grumpy x sunshine, green flag ML, alpha / strong FL, career-driven FL, workplace team bond, small town / island setting, second couple syndrome | J79: comfort drama, feel-good, healing & therapeutic, binge-worthy | K79: 7 | L79: https://pin.it/1VlkVe9hA | M79: https://pin.it/5QC32pTNa | N79: A highly energetic, former special forces member turned top sales representative for a major liquor company goes all out to save her local branch. Her mission requires her to recruit a brilliant, hyper-sensitive master brewer who can sense other people's emotions, triggering a clash of totally opposite personalities.
A80: Bridal mask | B80: series | C80: Korea | D80: 2012 | E80: 28 | F80: Completed | G80: Joo Won, Jin Se-Yeon, Han Chae-Ah, Park Ki-Woong | H80: action, historical, Drama, political, romance | I80: secret identity, undercover, dark justice, vigilante justice, enemies to lovers, second lead syndrome, tragic separation, tragic backstory, betrayal, red flag ML | J80: classic, Intense action, emotional rollercoaster | K80: 8.1 | L80: https://pin.it/5WAadanZ1 | M80: https://pin.it/5fYhY0duH | N80: Lee Kang-to is an ambitious Korean police officer working for the oppressive Japanese regime, reviled by his countrymen as a ruthless traitor. When a masked vigilante known as "Bridal Mask" protecting the innocent turns out to be tied to his own family's tragic past, Kang-to secretly dons the mask himself, living a dangerous double life as both a ruthless officer and a revolutionary hero.
A81: Bring it on, Ghost | B81: series | C81: Korea | D81: 2016 | E81: 16 | F81: Completed | G81: Ok Taec-Yeon, Kim So-Hyun, Kwon Yul, Kim Sang-Ho, Kang Ki-Young | H81: romcom, horror, fantasy, school | I81: Human x Supernatural Entity, supernatural abilities / powers, ghost / spirit, Co-habitation / living together, forced proximity, contract relationship, partners in crime, university / campus, highschool setting, Memory Loss / amnesia, green flag ML, She-Falls-First, hate to tolerance to love | J81: feel-good, chaotic fun, easy watch, emotional rollercoaster | K81: 7.6 | L81: https://pin.it/6cGcK7L7e | M81: https://pin.it/2NBWAxlIe | N81: Park Bong-pal is a lonely university student who uses his supernatural ability to see and punch ghosts to work as a profitable part-time exorcist, saving money to remove his cursed eyes. He encounters Kim Hyun-ji, a feisty, wandering high school ghost who has been suffering from memory loss for five years. Discovering that kissing Bong-pal triggers brief flashbacks of her past life, she convinces him to become her live-in ghostbusting partner, sparking a comedic romance.
A82: Bubblegum | B82: series | C82: Korea | D82: 2015 | E82: 16 | F82: Completed | G82: Lee Dong-Wook, Jung Ryeo-Won, Lee Jong-Hyuk 1, Park Hee-Von, Bae Jong-Ok, Lee Seung-Joon | H82: romcom, Drama, slice-of-life | I82: friends to lovers, first love, secret dating, healing romance, comfort romance, friends group, character growth, overcoming trauma, childhood trauma, adult life struggles, grief & loss, family dynamics, tragic backstory | J82: healing & therapeutic, emotional rollercoaster, aesthetically beautiful | K82: 6.3 | L82: https://pin.it/7xuyMG7aD | M82: https://pin.it/KgIAwmtih | N82: A compassionate eastern medicine doctor and an energetic radio producer have been completely inseparable since early childhood, acting more like protective family than friends. As they enter adulthood, they must confront their hidden, lingering feelings for each other while dealing with complex family opposition and deep emotional scars.
A83: Bulgasal: immortal souls | B83: series | C83: Korea | D83: 2022 | E83: 16 | F83: Completed | G83: Lee Jin-Wook, Kwon Nara, Lee Joon, Gong Seung-yeon, Jung Jin-Young, Kim Woo-Seok, Park Myung-Shin | H83: fantasy, Drama, thriller, mystery | I83: fated / destined love, reincarnation, past-life connection, curse / spell, Human x Supernatural Entity, magical element, epic romance, tragic separation, investigation, serial killer hunt, protective ML, alpha / strong FL, found family | J83: episode 1 hook, plot twist heavy, dark & heavy, aesthetically beautiful | K83: 7.4 | L83: https://pin.it/7wMuwJk65 | M83: https://pin.it/33bx4Xnwk | N83: A cursed man who has lived as an immortal being for over 600 years hunts for the reincarnation of the woman who stole his soul and made him a monster. Across centuries of death and rebirth, their paths cross with an array of characters, leading to an epic, dark fantasy battle for vengeance.
A84: Buried hearts | B84: series | C84: Korea | D84: 2025 | E84: 16 | F84: Completed | G84: Park Hyung-Sik, Heo Joon-Ho, Lee Hae-Young, Hong Hwa-Yeon, Woo Hyun, Kwon Soo-Hyun, Youn Sang-Hyun, Kim Jung-Nam | H84: crime, thriller, mystery, political, romance | I84: betrayal, tragic backstory, grief & loss, corruption / power abuse, mind games / psychological warfare, investigation, murder mystery, yearning / lovesick ML, top tier kiss, chemistry overload | J84: episode 1 hook, dark & heavy, emotional rollercoaster, underrated gem | K84: 7.3 | L84: https://pin.it/1HNM8xjyx | M84: https://pin.it/3GAG5vuL1 | N84: Seo Dong-ju, a talented executive at Daesan Group, secretly hacks into a massive political slush fund worth two trillion won. After being betrayed and targeted in a deadly attack, he survives but loses his memory. As the powerful people behind the missing money desperately try to recover it, Dong-ju becomes caught in a dangerous struggle involving corporate ambition, political power, betrayal, and revenge.
A85: Call it love | B85: series | C85: Korea | D85: 2023 | E85: 16 | F85: Completed | G85: Kim Young-Kwang, Lee Sung-Kyung, Sung Joon, Ahn Hee-Yeon, Kim Ye-Won | H85: melodrama, romance, slice-of-life, Drama | I85: hate to tolerance to love, revenge, hidden true self, workplace romance, slow burn romance, comfort romance, Bittersweet / Realistic romance, calm x calm, Calm x Chaotic, green flag ML, childhood trauma, adult life struggles, workplace setting, top tier kiss, character driven | J85: healing & therapeutic, emotional rollercoaster, "slow starter, worth it", aesthetically beautiful, underrated gem, comfort drama | K85: 7.7 | L85: https://pin.it/7m6vr0gp9 | M85: https://pin.it/5K8otvEze | N85: Sim Woo-joo’s life is completely ruined after she discovers her father's long-term infidelity, and her family is abruptly kicked out of their home by his mistress right after his sudden death. Driven by deep resentment, she plans a meticulous revenge by targeting Han Dong-jin—the mistress’s deeply lonely, workaholic, and emotionally exhausted son. However, as she gets closer to him and witnesses his own hidden misery, her thirst for vengeance blurs into unexpected, heartbreaking empathy.
A86: Can this love be translated? | B86: series | C86: Korea | D86: 2026 | E86: 12 | F86: Completed | G86: Kim Seon-Ho, Go Youn-Jung, Sota Fukushi, Lee E-Dam, Choi Woo-Sung, Kim Won-Hae | H86: romcom, fantasy | I86: She-Falls-First, mutual pining, second lead breaks your heart, second lead syndrome, healing romance, slow burn romance, workplace romance, forced proximity, top tier kiss, Calm x Chaotic, Celebrity x Normal Citizen, overseas / abroad setting, overcoming trauma, hidden true self, THE confrontation, chemistry overload, second couple syndrome, character driven | J86: aesthetically beautiful, OST is everything, feel-good, episode 1 hook | K86: 7.8 | L86: https://pin.it/a80uTzBXK | M86: https://pin.it/bjQqvaL95 | N86: A genius multilingual interpreter who prefers logical barriers over romantic messiness takes a job on an international travel dating show. He ends up translating for a top global actress hiding deep personal anxieties, leading them into a web of emotional misunderstandings as they struggle to find the right words for each other
A87: Captivating the king | B87: series | C87: Korea | D87: 2024 | E87: 16 | F87: Completed | G87: Jo Jung-Suk, Shin Se-Kyung, Lee Shin-Young, Park Ye-Young, Choi Dae-Hoon, Lee Gyu-Hoe, Yang Kyung-Won, Cho Seong-Ha, Son Hyun-Joo | H87: romance, melodrama, historical, political, Drama | I87: Joseon era, Palace intrigue, secret identity, enemies to lovers, revenge, betrayal, cold / tsundere ML, fated / destined love, Star-Crossed Lovers | J87: dark & heavy, plot twist heavy, emotional rollercoaster, aesthetically beautiful | K87: 7.6 | L87: https://pin.it/1I6uYvezr | M87: https://pin.it/4XKGFyOvR | N87: Lee In is a deeply lonely, emotionally exhausted prince caught in severe royal family friction, who finds true solace playing Baduk with an enigmatic, brilliant street player. When he ascends the throne as King, he is forced to become a cold-blooded ruler to survive intense palace intrigue. Years later, his old friend returns under a secret identity as a male Baduk master—but she is actually a fierce female spy seeking absolute political revenge.
A88: Cashero | B88: series | C88: Korea | D88: 2025 | E88: 8 | F88: Completed | G88: Lee Jun-Ho, Kim Hye-Jun, Kim Byung-Chul, Kim Hyang-Gi, Lee Chae-Min, Kang Han-Na | H88: action, fantasy, comedy, Drama, romance | I88: supernatural abilities / powers, supernatural strength, adult life struggles, underdog squad, partners in crime, corruption / power abuse, heist / robbery, Heroic Save, webtoon adaptation, chemistry overload | J88: chaotic fun, binge-worthy, Intense action | K88: 6.5 | L88: https://pin.it/62nmrokCj | M88: https://pin.it/4d37sypwS | N88: An ordinary, cash-strapped public servant suddenly inherits a unique family superpower: his physical strength scales exactly with the amount of cash he is holding. Alongside his highly practical girlfriend and a ragtag squad of calorie- and alcohol-fueled psychics, he takes on a corrupt elite organization.
A89: Castaway diva | B89: series | C89: Korea | D89: 2023 | E89: 12 | F89: Completed | G89: Park Eun-Bin, Chae Jong-Hyeop, Cha Hak-Yeon, Kim Hyo-Jin, Kim Jun-Han, Moon Woo-Jin, Lee Re | H89: romcom, slice-of-life, music | I89: friends to lovers, He-Falls-First, unrequited love, yearning / lovesick ML, K-pop Idol life, found family, childhood connection / first meeting, healing journey, character growth, secret identity, small town / island setting, second lead breaks your heart | J89: healing & therapeutic, emotional rollercoaster, underrated gem | K89: 7.8 | L89: https://pin.it/7gsP4C9CT | M89: https://pin.it/2Nuqsi2Xu | N89: An aspiring singer is rescued from a deserted island after being stranded completely alone for 15 years. Reentering a vastly changed modern world, she relentlessly pursues her childhood dream of becoming a pop diva while leaning on a supportive network of newfound allies and long-lost connections.
... A188: Forest | B188: series | C188: Korea | D188: 2020 | E188: 32 | F188: Completed | G188: Park Hae-Jin, Jo Bo-Ah, Jung Yeon-Joo, Noh Gwang-Sik | H188: psychological, romance, medical | I188: forced proximity, Co-habitation / living together, healing romance, small town / island setting, childhood trauma, CEO x Employee, overcoming trauma, secret past revealed, medical / hospital setting | J188: comfort drama, healing & therapeutic, easy watch, aesthetically beautiful | K188: 7.2 | L188: https://pin.it/vSv2Est91 | M188: https://pin.it/769aK5Dq7 | N188: Kang San-hyeok is an ambitious corporate M&A strategist who becomes a special rescue team member to acquire land inside a mysterious forest, despite suffering from phantom limb pain. There, he meets a passionate surgical resident banished to a rural hospital, and as the two share a home inside the ancient forest, they uncover forgotten childhood memories tied to the land.
A189: Four hands, two sonatas | B189: series | C189: Korea | D189: 2026 | E189: 12 | F189: Ongoing | G189: Song Kang, Lee Jun-Young, Jang Gyu-Ri, Kim Joo-Hun, Yoon Se-Ah, Jung Jin-Young | H189: music, romance, youth, Drama | I189: bromance, bromance steals the show, highschool setting, coming-of-age journey, childhood connection / first meeting, friends group, character growth, overcoming obstacles, academic pressure, class divide conflict, first love, love triangle | J189: emotional rollercoaster, healing & therapeutic | L189: https://pin.it/6RoYMkXTg | M189: https://pin.it/fQUZK9e0v | N189: Kang Pi-o is a perfectionist piano prodigy who has always stood at the top of his elite arts school. His carefully controlled world changes when Choi Jeong-yo, a naturally gifted pianist from a difficult background, arrives and challenges his position. What begins as intense rivalry develops into friendship and musical partnership as the two confront family pressure, personal wounds and the demands of becoming professional musicians.
A190: Fragile | B190: series | C190: Korea | D190: 2024 | E190: 8 | F190: Completed | G190: Kim So-Hui, Kim Eo-Jin, Gong Ju-Han, Kwon Hee-Song, Moon Ji-Won, Cha Ji-Hyeok | H190: youth, school, Drama, thriller | I190: highschool setting, school romance, toxic relationship, friends group, underdog squad, school bullying, academic pressure, hidden true self, coming-of-age journey, character growth | J190: plot twist heavy, binge-worthy, underrated gem, disappointing ending | K190: 6.2 | L190: https://pin.it/77kj2h9nQ | M190: https://pin.it/5GZUjqe8Z | N190: A raw, unfiltered youth drama that follows a group of high school students navigating the overwhelming pressures of academic failure, toxic friendships, and reckless romance. Facing the constant anxieties of modern teenage life, they find themselves pushed to the absolute brink of making reckless choices before their final graduation.
A191: Frankly speaking | B191: series | C191: Korea | D191: 2024 | E191: 12 | F191: Completed | G191: Go Kyung-Pyo, Kang Han-Na, Joo Jong-Hyuk, Shin Jung-Geun, Hwang Sung-Bin | H191: romcom, Drama | I191: workplace romance, He-Falls-First, second chance romance, mutual pining, slow burn romance, green flag ML, career-driven FL, emotionally guarded FL, Calm x Chaotic, workplace setting, workplace team bond, Celebrity x Normal Citizen | J191: chaotic fun, easy watch, feel-good, episode 1 hook | K191: 6.5 | L191: https://www.pinterest.com/pin/817333032422097238/ | M191: https://www.pinterest.com/pin/817333032422097235/ | N191: Popular news anchor Song Ki-baek suddenly loses his ability to filter what he says, making him brutally honest on live television and threatening his career. Variety-show writer On Woo-joo sees an opportunity in his unusual condition and brings him onto her program, where their professional relationship gradually develops into an unexpected romance.
A192: Friendly rivalry | B192: series | C192: Korea | D192: 2025 | E192: 16 | F192: Completed | G192: Lee Hye-Ri, Chung Su-Bin, Kang Hye-Won, Oh Woo-Ri, Kim Tae-Hoon, Choi Young-Jae | H192: mystery, psychological, school, youth, thriller | I192: highschool setting, academic pressure, school bullying, school corruption, Underdog vs. Elite, class divide conflict, Rich x Poor, toxic relationship, mind games / psychological warfare, betrayal, secret identity, hidden true self, psychopathic villain, sisterhood, secret past revealed, tragic backstory, k-trauma | J192: binge-worthy, plot twist heavy, ending will destroy you, aesthetically beautiful | K192: 7.7 | L192: https://pin.it/4od2GI3Rq | M192: https://pin.it/R0ACzx2qm | N192: An elite, hyper-competitive private all-girls high school is thrown into intense psychological warfare when a brilliant, mysterious transfer student arrives on campus. She instantly forms a toxic, deeply manipulative relationship with the school's top-ranking queen bee, sparking a dangerous academic war where friendship and obsession violently blur.
A193: From now on, showtime! | B193: series | C193: Korea | D193: 2022 | E193: 16 | F193: Completed | G193: Park Hae-Jin, Jin Ki-Joo, Jung Joon-Ho, Kim Won-Hae, Jung Suk-Yong | H193: fantasy, crime, mystery, romcom | I193: Human x Supernatural Entity, supernatural abilities / powers, ghost / spirit, magical element, partners in crime, investigation, serial killer hunt, hate to tolerance to love, forced proximity, Calm x Chaotic, grumpy x sunshine, cold / tsundere ML, protective ML, green flag ML, found family, past-life connection, secret past revealed | J193: chaotic fun, feel-good, easy watch, plot twist heavy, underrated gem | K193: 7.5 | L193: https://pin.it/5U47n9xIC | M193: https://pin.it/tZ2iv9tGt | N193: A cynical, world-famous stage magician performs seemingly impossible illusions using a secret squad of real, bickering ghosts whom he employs as his behind-the-scenes assistants. His highly lucrative lifestyle takes a wild turn when a passionate, supernatural-seeing female police officer enlists his ghost crew to help her solve supernatural crimes.
A194: Gangnam B-side | B194: series | C194: Korea | D194: 2024 | E194: 8 | F194: Completed | G194: Jo Woo-Jin, Ji Chang-Wook, Ha Yoon-Kyung, BIBI, Jung Ga-Ram, Oh Ye-Ju, Hyun Bong-Sik | H194: action, thriller, crime | I194: investigation, corruption / power abuse, cat-and-mouse chase, protective ML, alpha / strong FL, partners in crime, dark justice, street fights / hand-to-hand combat, tragic backstory, no romance, chemistry overload | J194: episode 1 hook, binge-worthy, fast-paced, plot twist heavy, dark & heavy | K194: 7.1 | L194: https://pin.it/2Uq8icUCm | M194: https://pin.it/5FSKq8b8C | N194: A demoted detective, a rogue street fixer, and an ambitious prosecutor team up to find a missing club hostess holding a devastating secret. Together, they are pulled into a treacherous, drug-fueled criminal conspiracy involving Gangnam's wealthiest elites and corrupt cops.
A195: Gaus electronics | B195: series | C195: Korea | D195: 2022 | E195: 12 | F195: Completed | G195: Kwak Dong-Yeon, Ko Sung-Hee, Bae Hyun-Sung, Kang Min-Ah | H195: comedy, romcom, slice-of-life | I195: workplace team bond, workplace romance, grumpy x sunshine, secret identity, hidden true self, Rich x Poor, friends group, adult life struggles, family dynamics, unnecessary misunderstanding, character growth, Chaotic x Chaotic, second couple syndrome, hate to tolerance to love | J195: chaotic fun, feel-good, comfort drama, easy watch, rewatchable, binge-worthy, underrated gem | K195: 7.8 | L195: https://pin.it/6DY2LmkXu | M195: https://pin.it/CwOGpYOrU | N195: An oblivious employee who constantly causes accidental chaos and his short-tempered senior assistant manager clash in Marketing Team 3—the corporate dumping ground for eccentric corporate misfits. Alongside a hidden billionaire heir working as an entry-level intern, they face a chaotic office survival battlefield.
A196: Genie, make a wish | B196: series | C196: Korea | D196: 2025 | E196: 13 | F196: Completed | G196: Kim Woo-Bin, Bae Suzy, Ahn Eun-Jin, Steve Noh, Lee Joo-Young, Go Gyu-Pil | H196: romcom, fantasy, Drama | I196: Human x Supernatural Entity, curse / spell, Calm x Chaotic, grumpy x sunshine, Co-habitation / living together, yearning / lovesick ML, fated / destined love, reincarnation, tragic backstory, secret past revealed, chemistry overload | J196: binge-worthy, chaotic fun | K196: 6.6 | L196: https://pin.it/1FM8gDfJN | M196: https://pin.it/5iFyBUB8e | N196: An overly emotional genie who has been trapped inside a lamp for centuries is finally awakened by an emotionally detached, cold-hearted woman who seems immune to his magical charm. Granted three life-changing wishes, the stoic woman tests the volatile genie's patience as their chaotic dynamic slowly morphs into deep mutual healing and unexpected romance.
A197: Ghost doctor | B197: series | C197: Korea | D197: 2022 | E197: 16 | F197: Completed | G197: Rain, Kim Bum, Uee, Son Na-Eun, Sung Dong-Il | H197: fantasy, medical, comedy, Drama | I197: soul swap, hidden true self, workplace team bond, character growth, bromance, ghost / spirit, Human x Supernatural Entity, medical / hospital setting, Heroic Save, found family | J197: feel-good, comfort drama, chaotic fun, easy watch, binge-worthy | K197: 7.9 | L197: https://pin.it/7fjHvBdR2 | M197: https://pin.it/1gOgQcMtf | N197: An arrogant, cold-hearted thoracic surgeon ends up in a coma as a wandering ghost who can only possess a clumsy, first-year resident who is a genius in theory but terrified in practice. Bound together, this contrasting medical duo must share one body to perform miraculous surgeries and uncover a hospital conspiracy.
A198: Girls' generation 1979 | B198: series | C198: Korea | D198: 2017 | E198: 8 | F198: Completed | G198: Bona, Chae Seo-Jin, Seo Young-Joo, Lee Jong-Hyun, Yeo Hoi-Hyun, Min Do-Hee | H198: youth, Drama, romance | I198: highschool setting, coming-of-age journey, first love, unrequited love, friends to lovers, sisterhood, retro / period setting, family dynamics, overcoming obstacles, class divide conflict, small town / island setting, character growth | J198: underrated gem, comfort drama, healing & therapeutic, feel-good | K198: 7.4 | L198: https://pin.it/3Rauusjvs | M198: https://pin.it/25RKyFSdx | N198: Set in 1970s Daegu, a bubbly high school girl navigates teen romance and family expectations until a sophisticated transfer student from Seoul arrives and captures all the local boys' attention. Their complex initial rivalry eventually evolves into a deep, poignant female friendship as they face the harsh realities of a conservative society.
A199: Go back couple | B199: series | C199: Korea | D199: 2017 | E199: 12 | F199: Completed | G199: Son Ho-Jun, Jang Na-Ra, Heo Jung-Min, Han Bo-Reum, Jang Ki-Yong, Go Bo-Gyeol, Lee Yi-Kyung, Cho Hye-Jung | H199: fantasy, romcom, Drama, family | I199: time travel, second chance romance, university / campus, adult life struggles, Bittersweet / Realistic romance, healing romance, second lead syndrome, right person wrong time, love triangle, first love, unresolved feelings, Co-habitation / living together, friends group, family dynamics, hate to tolerance to love | J199: masterpiece, cry fest, feel-good, rewatchable, emotional rollercoaster, comfort drama | K199: 8.1 | L199: https://pin.it/7nU36SGYY | M199: https://pin.it/4pO1Xf8oE | N199: Exhausted by financial struggles, parenting, and marital drift, a 38-year-old married couple reach their breaking point and throw away their wedding rings. The very next morning, they wake up as 20-year-old university students back in 1999 with their adult memories intact, granting them the chance to make entirely different choices—or rediscover why they fell in love in the first place.
A200: Goblin | B200: series | C200: Korea | D200: 2016 | E200: 16 | F200: Completed | G200: Gong Yoo, Kim Go-Eun, Lee Dong-Wook, Yoo In-Na, Yook Sung-Jae, Lee El | H200: fantasy, romance, melodrama, comedy | I200: fated / destined love, past-life connection, reincarnation, age gap romance, Co-habitation / living together, forced proximity, bromance, tragic separation, found family, protective ML, tragic backstory, secret past revealed, supernatural abilities / powers, demon / deity, older ML (oppa), second couple syndrome, chemistry overload | J200: masterpiece , classic, emotional rollercoaster, ending will destroy you, aesthetically beautiful, OST is everything, episode 1 hook, cry fest | K200: 8.5 | L200: https://pin.it/1k0tiQILb | M200: https://pin.it/2hzvxl9tS | N200: An immortal, centuries-old general turned Goblin must find his destined mortal bride to finally pull a cursed sword from his chest and end his eternal life. His lonely existence takes a chaotic turn when he ends up cohabitating with an amnesiac Grim Reaper and meets a bright high school student who can see ghosts.A devastated television writer whose young daughter is kidnapped and murdered gets a miraculous second chance when she wakes up exactly 14 days before the horrific crime. Teaming up with a rogue private investigator, she enters a frantic race against time to decipher cryptic clues and stop the serial killer.
A201: God's gift: 14 days | B201: series | C201: Korea | D201: 2014 | E201: 16 | F201: Completed | G201: Lee Bo-Young, Cho Seung-Woo, Kim Tae-Woo, Kim Yoo-Bin, Jung Gyu-Woon | H201: thriller, mystery, psychological, crime | I201: time travel, partners in crime, investigation, murder mystery, serial killer hunt, cat-and-mouse chase, secret past revealed, betrayal, corruption / power abuse, tragic backstory | J201: episode 1 hook, binge-worthy, fast-paced, plot twist heavy, dark & heavy, disappointing ending | K201: 7.8 | L201: https://pin.it/53WhtJgOZ | M201: https://pin.it/2Pr2hS42M | N201: A devastated television writer whose young daughter is kidnapped and murdered gets a miraculous second chance when she wakes up exactly 14 days before the horrific crime. Teaming up with a rogue private investigator, she enters a frantic race against time to decipher cryptic clues and stop the serial killer.
... A319: Made in Korea | B319: series | C319: Korea | D319: 2025 | E319: 6 | F319: Completed | G319: Hyun Bin, Jung Woo-Sung, Seo Eun-Soo, Won Ji-An, Kang Gil-Woo, Jung Sung-Il, Roh Jae-Won, Woo Do-Hwan, Lee Ju-Yeon | H319: crime, political, Drama, thriller, action | I319: retro / period setting, corruption / power abuse, Underdog vs. Elite, mind games / psychological warfare, betrayal, street fights / hand-to-hand combat, gangsters / mafia, dark justice, workplace setting, tragic backstory | J319: dark & heavy, plot twist heavy, Intense action, binge-worthy | K319: 7.3 | L319: https://pin.it/2o6pS1SVh | M319: https://pin.it/5PojaFIZu | N319: Set during the turbulent, rapid economic expansion of 1970s South Korea, Baek Ki-tae is an ambitious, power-hungry man driven by an insatiable desire for wealth and influence. His ruthless rise to power brings him into direct collision with Jang Geon-young, a fiercely principled prosecutor who will stop at nothing to dismantle the corrupt networks governing the nation, sparking a high-stakes battle of intellect and political ambition.
A320: Made in korea 2 | B320: series | C320: Korea | D320: 2026 | E320: 6 | F320: Completed | G320: Hyun Bin, Jung Woo-Sung, Woo Do-Hwan, Seo Eun-Soo, Won Ji-An, Jung Sung-Il, Jang Hye-Jin, Roh Jae-Won | H320: crime, political, Drama, thriller, action | I320: retro / period setting, corruption / power abuse, Underdog vs. Elite, mind games / psychological warfare, betrayal, gangsters / mafia, dark justice, cat-and-mouse chase | J320: dark & heavy, plot twist heavy, Intense action, binge-worthy, ending will destroy you | L320: https://pin.it/5fF0Pm3Fa | M320: https://pin.it/llDl52g8E | N320: Nine years after the events of the first season, Baek Ki-tae has reached the height of his power while prosecutor Jang Geon-young has spent years preparing his counterattack. Meanwhile, Baek Ki-hyun, Ki-tae's younger brother, pursues his own path toward power, creating a dangerous new conflict within the family. As the ambitions of the three men collide, political power, family loyalty, and personal revenge threaten to tear everything apart.
A321: Maestra: Strings of Truth | B321: series | C321: Korea | D321: 2023 | E321: 12 | F321: Completed | G321: Lee Young-Ae, Lee Mu-Saeng, Hwang Boreum-Byeol, Kim Min-Kyu | H321: Drama, music, mystery, psychological | I321: workplace romance, career-driven FL, alpha / strong FL, unresolved feelings, toxic relationship, secret past revealed, tragic backstory, investigation, murder mystery, mind games / psychological warfare, corruption / power abuse, workplace team bond, character growth, overcoming trauma | J321: dark & heavy, plot twist heavy, emotional rollercoaster, aesthetically beautiful, OST is everything | K321: 7.1 | L321: https://pin.it/NYfLDaNKj | M321: https://pin.it/3rxfeG97p | N321: Cha Se-eum, a world-class conductor who has built a career abroad, returns to Korea to take over the struggling Hangang Philharmonic Orchestra. Determined to transform the orchestra, she encounters resistance from its members while secrets from her own past and mysterious incidents within the orchestra threaten to destroy everything she has built.
A322: Marry my husband | B322: series | C322: Korea | D322: 2024 | E322: 16 | F322: Completed | G322: Park Min-Young, Na In-Woo, Lee Yi-Kyung, Song Ha-Yoon, Lee Gi-Kwang, Gong Min-Jung | H322: fantasy, romcom, Drama, romance | I322: time travel, revenge, betrayal, second chance romance, fated / destined love, green flag ML, protective ML, yearning / lovesick ML, alpha / strong FL, career-driven FL, workplace romance, CEO x Employee, chaebol family drama, fake dating, webtoon adaptation, toxic relationship, top tier kiss | J322: episode 1 hook, binge-worthy, fast-paced, plot twist heavy, emotional rollercoaster, chaotic fun | K322: 7.8 | L322: https://pin.it/3M4VmBpKB | M322: https://pin.it/1QM4nIZEJ | N322: Kang Ji-won is a terminally ill woman who discovers that her selfish husband is having an affair with her duplicitous best friend, only to be murdered by them during a confrontation. Miraculously waking up ten years in the past, she gets a second chance at life and vows to rewrite her tragic fate. Joining forces with Yoo Ji-hyuk, her capable and supportive corporate director, she systematically orchestrates a plan to manipulate her cheating husband and fake friend into marrying each other instead.
A323: Mask girl | B323: series | C323: Korea | D323: 2023 | E323: 7 | F323: Completed | G323: Lee Han-Byeol, Nana, Go Hyun-jung, Ahn Jae-Hong, Yeom Hye-Ran | H323: thriller, crime, psychological, Drama | I323: secret identity, hidden true self, dark comedy, psychopathic villain, accidental murder / witness, framed for a crime, cat-and-mouse chase, prison setting, toxic relationship, revenge, multiple leads, webtoon adaptation, no romance | J323: dark & heavy, plot twist heavy, gory & violent, binge-worthy, underrated gem | K323: 7.3 | L323: https://pin.it/SP3Us5X6S | M323: https://pin.it/9b3zodx13 | N323: Kim Mo-mi is an ordinary, insecure office worker who has always dreamed of being a performer but suffers from deep self-consciousness about her appearance. By night, she wears a mask and lives a double life as a wildly popular live-stream personality known as Mask Girl. When a series of unexpected, violent events unravels her secret online identity, she is dragged into a dark, blood-soaked downward spiral of murder, plastic surgery, and absolute obsession.
A324: May I help you | B324: series | C324: Korea | D324: 2022 | E324: 16 | F324: Completed | G324: Lee Hye-Ri, Lee Jun-Young, Song Deok-Ho, Tae In-Ho, Lee Kyu-Han, Oh Dae-Hwan, Park Soo-Young, Seo Hye-Won | H324: fantasy, Drama, slice-of-life, comedy, romance | I324: ghost / spirit, supernatural abilities / powers, healing romance, comfort romance, green flag ML, career-driven FL, workplace romance, found family, neighborhood squad, healing journey, overcoming trauma, grief & loss, life lessons, secret past revealed, tragic backstory | J324: healing & therapeutic, comfort drama, feel-good, emotional rollercoaster, cry fest, underrated gem | K324: 7.6 | L324: https://pin.it/5DftnSqA3 | M324: https://pin.it/5DftnSqA3 | N324: Baek Dong-joo is a compassionate funeral director who possesses a supernatural gift: when she touches the dead, they temporarily wake up to share their final wishes. She teams up with Kim Jib-sa, a versatile errand boy for a local pay-per-task business called "Irosundong." Together, they work through strange, funny, and deeply emotional requests to fulfill the last desires of the deceased, healing their own personal grief along the way.
A325: Melancholia | B325: series | C325: Korea | D325: 2021 | E325: 16 | F325: Completed | G325: Im Soo-Jung, Lee Do-Hyun, Jin Kyung, Choi Dae-Hoon | H325: Drama, melodrama, school, romance | I325: age gap romance, school corruption, Underdog vs. Elite, academic pressure, highschool setting, Teacher x Student, framed for a crime, revenge, healing romance, slow burn romance, protective ML, career-driven FL, character growth, overcoming trauma, older FL (noona), character driven | J325: aesthetically beautiful, "slow starter, worth it", emotional rollercoaster, underrated gem | K325: 7.3 | L325: https://pin.it/128fALHoD | M325: https://pin.it/6laIkzqBO | N325: Ji Yoon-soo is a passionate, non-traditional mathematics teacher at a prestigious private high school rampant with systemic corruption and academic favoritism. She recognizes the raw, untamed genius of Baek Seung-yoo, a quiet, traumatized math prodigy who has closed off his heart to the world. When corrupt administrators spread a malicious scandal framing their mentor-student bond as inappropriate, their lives are shattered, leading to a fiery story of redemption and revenge years later.
A326: Melo movie | B326: series | C326: Korea | D326: 2025 | E326: 10 | F326: Completed | G326: Choi Woo-Shik, Park Bo-Young, Lee Jun-Young, Jeon So-Nee, Kim jae-Uck, Cha Woo-Min, Ko Chang-Seok | H326: romcom, romance, slice-of-life, Drama | I326: workplace romance, friends to lovers, Golden Retriever ML, yearning / lovesick ML, career-driven FL, alpha / strong FL, adult life struggles, life lessons, healing romance, overcoming trauma, Calm x Chaotic, chemistry overload, second couple syndrome, character driven | J326: healing & therapeutic, aesthetically beautiful, underrated gem | K326: 7.2 | L326: https://pin.it/1wWZ8ipJu | M326: https://pin.it/bTsUJXLFG | N326: A heartwarming, realistic story exploring the dreams, failures, and romantic lives of young adults navigating the competitive film and entertainment industry. Following an aspiring film director carrying unresolved emotional baggage and a cynical movie critic who hides his own vulnerabilities, the drama captures how young people learn to love, heal, and craft their own life narratives despite constant setbacks.
A327: Melting me softly | B327: series | C327: Korea | D327: 2019 | E327: 16 | F327: Completed | G327: Ji Chang-Wook, Won Jin-Ah, Yoon Se-Ah, Im Won-Hee | H327: romcom, fantasy, comedy, romance, sci-fi | I327: Frozen in Time, forced proximity, Co-habitation / living together, workplace romance, secret past revealed, protective ML, career-driven FL, clumsy FL, family dynamics, CEO x Employee, top tier kiss, chemistry overload, hate to tolerance to love | J327: chaotic fun, easy watch, underrated gem | K327: 6.8 | L327: https://pin.it/4fAoQPupw | M327: https://pin.it/st1OfCChs | N327: Ma Dong-chan, a star television variety show producer, and Go Mi-ran, a brave college student working as an experimental subject, participate in a 24-hour cryonics project for a groundbreaking broadcast. Due to a mysterious conspiracy, they wake up 20 years later instead, retaining their youthful bodies while the world around them has aged. To stay alive, both must maintain a core body temperature of 31.5°C, making falling in love a literal life-threatening challenge.
A328: Memories of the alhambra | B328: series | C328: Korea | D328: 2018 | E328: 16 | F328: Completed | G328: Hyun Bin, Park Shin-Hye, Park Hoon, Kim Eui-Sung, Lee Seung-Joon | H328: sci-fi, thriller, mystery, fantasy, romance, action | I328: tech-driven romance, overseas / abroad setting, fated / destined love, survival thriller, murder mystery, psychopathic villain, supernatural abilities / powers, mind games / psychological warfare, protective ML, alpha / strong FL, tragic backstory, betrayal, unresolved feelings , hidden true self | J328: episode 1 hook, plot twist heavy, Intense action, dark & heavy, aesthetically beautiful, disappointing ending | K328: 7.7 | L328: https://pin.it/5xNpZslXV | M328: https://pin.it/1dL910aYJ | N328: Yoo Jin-woo is the brilliant, driven CEO of an investment firm who travels to Granada, Spain, to buy a revolutionary, hyper-realistic augmented reality game. Checking into a run-down hostel managed by Jung Hee-joo, an earnest classic guitarist, he gets pulled into the game's immersive virtual world. However, when a glitch in the software causes in-game deaths to translate into real-world fatalities, Jin-woo finds himself hunted by deadly digital enemies while trying to keep his sanity.
A329: Memorist | B329: series | C329: Korea | D329: 2020 | E329: 16 | F329: Completed | G329: Yoo Seung-Ho, Lee Se-Young, Cho Seong-Ha, Ko Chang-Seok, Yun Ji-On | H329: thriller, mystery, crime, action | I329: supernatural abilities / powers, murder mystery, serial killer hunt, investigation, cat-and-mouse chase, psychopathic villain, mind games / psychological warfare, partners in crime, alpha / strong FL, career-driven FL, protective ML, tragic backstory, secret past revealed, corruption / power abuse, dark justice, no romance, webtoon adaptation | J329: episode 1 hook, fast-paced, binge-worthy, plot twist heavy, dark & heavy, Intense action | K329: 7.6 | L329: https://pin.it/6PLIN6wt4 | M329: https://pin.it/2bvO65SGC | N329: Dong Baek is an extraordinary detective with the supernatural ability to instantly read a person's memories simply by touching them. Operating as a public celebrity cop, his aggressive tactics draw intense scrutiny. He pairs up with Han Sun-mi, an elite, brilliant criminal profiler who relies strictly on sharp logic and data. Together, they pursue a terrifying serial killer with dangerous powers of their own, uncovering high-level political corruption along the way.
A330: Mercy for none | B330: series | C330: Korea | D330: 2025 | E330: 7 | F330: Completed | G330: So Ji-Sub, Heo Joon-Ho, Ahn Kil-Kang, Lee bum-Soo, Gong Myung, Choo Young-Woo, Jo Han-Chul, Jung Gun-Joo, Lee Jun-Hyuk | H330: action, crime, thriller | I330: revenge, gangsters / mafia, street fights / hand-to-hand combat, dark justice, vigilante justice, betrayal, tragic backstory, no romance, webtoon adaptation | J330: gory & violent, Intense action, dark & heavy, episode 1 hook, fast-paced | K330: 7.5 | L330: https://pin.it/1DzWJllUZ | M330: https://pin.it/1rKD3Uu0I | N330: Nam Ki-joon, a feared former gangster who cut ties with the underworld after his younger brother's mysterious death, is pulled back into the violent shadows he swore to leave behind. Driven by unyielding fury, he launches a ruthless, single-handed war against the powerful crime syndicates and corrupt figures involved, tearing through every obstacle in his path to extract total retribution.
A331: Military prosecutor doberman | B331: series | C331: Korea | D331: 2022 | E331: 16 | F331: Completed | G331: Ahn Bo-Hyun, Jo Bo-Ah, Oh Yeon-Soo, Kim Young-Min, Kim Woo-Seok, Kang Mal-Geum | H331: military, legal, action, crime, Drama | I331: military setting, legal / courtroom setting, revenge, dark justice, vigilante justice, corruption / power abuse, partners in crime, alpha / strong FL, career-driven FL, cold / tsundere ML, protective ML, undercover, hidden true self, street fights / hand-to-hand combat, Underdog vs. Elite | J331: episode 1 hook, fast-paced, binge-worthy, Intense action, chaotic fun | K331: 7.7 | L331: https://pin.it/33DPVoPGV | M331: https://pin.it/14ZBl3z6m | N331: Do Bae-man is a cynical, money-driven military prosecutor who took the job solely to secure wealth and early retirement. He collides with Cha Woo-in, a confident rookie military prosecutor from a wealthy family who hides an exceptional martial arts capability and a secret desire for revenge against military corruption. Joining forces, the two work together to tear down the rotten, entrenched power structures that protect criminals inside the armed forces.
A332: Misaeng: incomplete life | B332: series | C332: Korea | D332: 2014 | E332: 20 | F332: Completed | G332: Im Si-Wan, Lee Sung-Min, Kang So-Ra, Kang Ha-Neul, Byun Yo-Han, Kim Dae-Myung | H332: Drama, slice-of-life | I332: workplace setting, workplace team bond, adult life struggles, Underdog vs. Elite, no romance, coming-of-age journey, underdog squad, academic pressure, bromance, career-driven FL, life lessons, character growth, multiple leads, character driven | J332: masterpiece, healing & therapeutic, easy watch, rewatchable, emotional rollercoaster | K332: 8.5 | L332: https://pin.it/7hq5BL5cR | M332: https://pin.it/6NbzLNtCE | N332: Armed with only a high school equivalency diploma and years of playing the board game Go, Jang Geu-rae lands an internship at a massive international trading corporate firm through a referral. Lacking corporate knowledge, he applies the strategic principles of Go to survive corporate politics, harsh deadlines, and personal inadequacy alongside his quirky team.
... A348: Mouse | B348: series | C348: Korea | D348: 2021 | E348: 20 | F348: Completed | G348: Lee Seung-Gi, Lee Hee-Joon, Park Ju-Hyun, Gyeong Su-Jin | H348: thriller, mystery, crime, psychological, sci-fi | I348: murder mystery, serial killer hunt, investigation, psychopathic villain, mind games / psychological warfare, secret past revealed, tragic backstory, framed for a crime, cat-and-mouse chase, dark justice, medical / hospital setting, childhood trauma, no romance | J348: masterpiece , plot twist heavy, episode 1 hook, binge-worthy, dark & heavy, gory & violent, fast-paced, emotional rollercoaster | K348: 8.6 | L348: https://pin.it/4oIPevZjP | M348: https://pin.it/36nFVQng7 | N348: In a world where a genetic test can identify psychopaths in the womb, Jeong Ba-reum is a kind, honest rookie police officer whose life changes forever after a violent encounter with a ruthless, head-hunting serial killer. Teaming up with Go Moo-chi, a hardened detective driven by vengeance after his parents were murdered in his childhood, Ba-reum pursues a terrifying predator, only to unravel mind-bending truths about his own mind.
A349: Mousetrap | B349: series | C349: Korea | D349: 2026 | E349: 10 | F349: Completed | G349: Ryu Jun-Yeol, Lee Kyu-Hyung, Sul Kyung-Gu, Kim Yoon-Tae, Kim Jung-young, Song Su-Yi, Park Yoon-Ho, Jung Hee-Tae, Kim Sung-Oh, Hyun Bong-Sik, Moo Jin-Sung | H349: thriller, mystery, psychological, crime | I349: mistaken identity, secret identity, framed for a crime, investigation, mind games / psychological warfare, cat-and-mouse chase, gangsters / mafia, hostage situation, secret past revealed, dark justice, survival thriller, betrayal, webtoon adaptation | J349: dark & heavy, plot twist heavy, fast-paced, Intense action | L349: https://pin.it/3rwfV4NTD | M349: https://pin.it/77VmDBg97 | N349: Reclusive novelist Moon-jae wakes to discover that his identity has effectively been stolen by a mysterious doppelgänger known as “The Rat.” Stripped of his name, money and ability to prove who he is, he turns to ruthless loan shark Noja for help. Together, they enter a dangerous world of identity laundering and deception while a detective closes in on the truth.
A350: Move to heaven | B350: series | C350: Korea | D350: 2021 | E350: 10 | F350: Completed | G350: Lee Je-Hoon, Tang Jun-Sang, Hong Seung-Hee, Jung Suk-Yong, Jung Young-Joo, Im Won-Hee | H350: slice-of-life, Drama, family, melodrama | I350: found family, family dynamics, grief & loss, life lessons, adult life struggles, prison setting, street fights / hand-to-hand combat, tragic backstory, character growth, healing journey, no romance, k-trauma, character driven | J350: masterpiece , cry fest, healing & therapeutic, comfort drama, feel-good, emotional rollercoaster, underrated gem, binge-worthy | K350: 8.5 | L350: https://pin.it/2106PVPmS | M350: https://pin.it/27UFaufXs | N350: Han Geu-ru is a young man with Asperger's syndrome who works alongside his father at "Move to Heaven," a trauma cleaning business that arranges the possessions left behind by the deceased to deliver their unspoken final messages to loved ones. When his father suddenly dies, Geu-ru's guardianship is handed to Cho Sang-goo, a cynical ex-convict and underground fighter. Together, the mismatched pair continue the business, discovering profound truths about life and humanity.
A351: Moving | B351: series | C351: Korea | D351: 2023 | E351: 20 | F351: Completed | G351: Ryu Seung-Ryong, Han Hyo-Joo, Zo In-Sung, Lee Jung-Ha, Go Youn-Jung, Kim Do-Hoon, Cha Tae-Hyun, Ryu Seung-Beom, Kim Sung-Kyun, Kim Hee-Won | H351: action, thriller, sci-fi, youth, school, romance | I351: supernatural abilities / powers, supernatural strength, highschool setting, school romance, first love, protective ML, green flag ML, alpha / strong FL, career-driven FL, family dynamics, undercover, secret identity, secret past revealed, tragic backstory, street fights / hand-to-hand combat, corruption / power abuse, multiple leads, webtoon adaptation, chemistry overload, second couple syndrome | J351: masterpiece , episode 1 hook, Intense action, gory & violent, plot twist heavy, dark & heavy | K351: 8.4 | L351: https://pin.it/2TqkCkMbT | M351: https://pin.it/RCcNDU9Q8 | N351: Kim Bong-seok, Jang Hee-soo, and Lee Gang-hoon are three high school students who appear ordinary but harbor extraordinary, inherited superpowers, including levitation, super-healing, and super-strength. While trying to keep their abilities hidden from the world, their parents—former covert intelligence operatives—must come out of hiding to protect their children from a mysterious killer hunting down individuals with special powers.
A352: Moving 2 | B352: series | C352: Korea | E352: 16 | F352: Upcoming | G352: Ryu Seung-Ryong, Han Hyo-Joo, Zo In-Sung, Go Youn-Jung, Kim Do-Hoon, Won Gyu Bin, Cha Tae-Hyun, Ryu Seung-Beom, Kim Sung-Kyun, Kim Hee-Won | H352: action, thriller, sci-fi, Drama | I352: supernatural abilities / powers, supernatural strength, family dynamics, undercover, secret identity, hidden true self, street fights / hand-to-hand combat, corruption / power abuse, Underdog vs. Elite, survival thriller, multiple leads, partners in crime, webtoon adaptation | J352: episode 1 hook, Intense action, gory & violent, plot twist heavy, dark & heavy | N352: Picking up after the explosive events of the initial showdown, the next generation of superpowered individuals faces escalating global threats as rogue covert agencies and international organizations attempt to weaponize their abilities. With their parents fighting alongside them, the young heroes must master their dangerous powers to defend their families and secure their freedom against new enemies.
A353: Mr. Plankton | B353: series | C353: Korea | D353: 2024 | E353: 10 | F353: Completed | G353: Woo Do-Hwan, Lee Yoo-Mi, Oh Jung-Se, Kim Hae-Sook, Kim Min-Seok, Lee El, Oh Dae-Hwan | H353: romcom, comedy, romance, Drama, slice-of-life | I353: forced proximity, contract relationship, right person wrong time, tragic separation, Bittersweet / Realistic romance, character growth, adult life struggles, grief & loss, life lessons, protective ML, alpha / strong FL, clumsy FL, top tier kiss, chemistry overload, k-trauma | J353: emotional rollercoaster, cry fest, chaotic fun, binge-worthy, aesthetically beautiful, ending will destroy you | K353: 8.1 | L353: https://pin.it/45CljhTPF | M353: https://pin.it/7KDb5POju | N353: Hae Jo is a man born out of a mistake who has lived an aimless, rootless life with no family connections, feeling like plankton floating in the ocean. When he receives news that radically alters his remaining lifespan, he embarks on a final journey to find his biological father. Joining him on his wild road trip is Jo Jae-mi, the world's unluckiest bride-to-be, who is dragged away right before her wedding to an aristocratic family.
A354: Mr. Queen | B354: series | C354: Korea | D354: 2020 | E354: 20 | F354: Completed | G354: Shin Hye-Sun, Kim Jung-Hyun, Bae Jong-Ok, Kim Tae-Woo, Na In-Woo, Seol In-Ah, Jeon Bae-Soo | H354: historical, comedy, romcom, fantasy, political, romance | I354: soul swap, time travel, gender bender, Joseon era, Palace intrigue, enemies to lovers, contract relationship, Co-habitation / living together, forced proximity, hidden true self, secret identity, alpha / strong FL, career-driven FL, cold / tsundere ML, protective ML, street fights / hand-to-hand combat, top tier kiss, chemistry overload, Chaotic x Chaotic | J354: masterpiece , chaotic fun, feel-good, rewatchable, binge-worthy, episode 1 hook, OST is everything | K354: 8.5 | L354: https://pin.it/4pRs1e5eQ | M354: https://pin.it/5lw6r8NEA | N354: Jang Bong-hwan is a confident, modern-day chef working in the Blue House who, after a near-fatal accident, finds his soul magically trapped inside the body of Queen Cheorin in the Joseon era. While navigating the strict royal court as a woman with a boisterous male personality, he gets involved with King Cheoljong, a monarch who appears to be a weak puppet on the surface but secretly harbors a sharp intelligence to reform his kingdom.
A355: Mr. sunshine | B355: series | C355: Korea | D355: 2018 | E355: 24 | F355: Completed | G355: Lee Byung-Hun, Kim Tae-Ri, Yoo Yeon-Seok, Byun Yo-Han, Kim Min-Jung, Kim Kap-Soo, Choi Mu-Sung, Kim Eui-Sung | H355: historical, romance, melodrama, action, political | I355: retro / period setting, Joseon era, Palace intrigue, epic romance, fated / destined love, forbidden love, Star-Crossed Lovers, tragic separation, right person wrong time, love triangle, protective ML, yearning / lovesick ML, alpha / strong FL, career-driven FL, street fights / hand-to-hand combat, corruption / power abuse, class divide conflict, bromance steals the show, multiple leads, older ML (oppa), k-trauma | J355: ending will destroy you, emotional rollercoaster, aesthetically beautiful, Intense action, cry fest, dark & heavy, masterpiece, OST is everything | K355: 8.7 | L355: https://pin.it/7jJuT4Jxj | M355: https://pin.it/5J7TOyWd2 | N355: Eugene Choi was born into slavery in Joseon Korea but escaped to the United States aboard a warship during the 1871 Shinmiyangyo incident, returning years later as a captain in the US Marine Corps. Stationed in his homeland during the turn of the 20th century, he falls in love with Go Ae-shin, an aristocratic noblewoman who secretly operates as a sniper for the Righteous Army, joining her in a tragic fight for Korea's sovereignty.
A356: My beautiful bride | B356: series | C356: Korea | D356: 2015 | E356: 16 | F356: Completed | G356: Kim Mu-Yeol, Lee Si-Young, Ko Sung-Hee, Ryu Seung-Soo, Park Hae-Joon | H356: action, crime, thriller, romance, mystery | I356: protective ML, hidden true self, secret identity, street fights / hand-to-hand combat, gangsters / mafia, murder mystery, investigation, cat-and-mouse chase, dark justice, alpha / strong FL, secret past revealed, tragic backstory | J356: episode 1 hook, Intense action, fast-paced, dark & heavy, underrated gem | K356: 7.3 | L356: https://pin.it/1Zkzq9g1x | M356: https://pin.it/22tv1Zoio | N356: Kim Do-hyeong is a quiet, ordinary bank executive who is deeply in love with his sweet fiancée, Yoon Joo-young. When she suddenly vanishes without a trace right after he proposes, Do-hyeong unleashes a ruthless, relentless inner monster to find her. As he tears through the violent underbelly of loan shark syndicates and organized crime, dark secrets about Joo-young's past come to light.
A357: My bias, my boss | B357: series | C357: Korea | D357: 2026 | E357: 12 | F357: Completed | G357: Kang Hoon, Kim Hye-Jun, Cha Woo-Min, Gong Ji-Ho, Kim Ah-Young, Hwang Sung-Bin, Shin Yu-Na, Nam Hyeon-Woo, Lee Dam-Hee, Heo Joon-Seok, Jang Hyuk-Jin, Jang Hye-Jin | H357: romcom, Drama, romance | I357: He-Falls-First, secret dating, love triangle, second lead syndrome, workplace romance, top tier kiss, THE confrontation, Calm x Chaotic, CEO x Employee, Celebrity x Normal Citizen, career-driven FL, clumsy FL, sisterhood, workplace team bond, workplace setting, K-pop Idol life, unrequited love, chemistry overload, second couple syndrome, betrayal, bromance, cold / tsundere ML, green flag ML, Golden Retriever ML | J357: easy watch, rewatchable, feel-good, chaotic fun, binge-worthy | K357: 7.4 | L357: https://pin.it/7afPPFp4I | M357: https://pin.it/7JCuocy9d | N357: Nam Da-reum has spent years idolizing Lee Chan, so landing a job at the fashion company he co-founded seems like a dream come true. Instead, she finds herself working under Kang Ha-gi, Chan's prickly, workaholic childhood friend and CEO. As Da-reum tries to hide her fangirl identity, an unexpected workplace romance develops while the complicated feelings connecting the three begin to surface.
A358: My country: the new age | B358: series | C358: Korea | D358: 2019 | E358: 16 | F358: Completed | G358: Yang Se-Jong, Woo Do-Hwan, Kim Seol-Hyun, Jang Hyuk, Ahn Nae-Sang, Cho Yi-Hyun, In Gyo-Jin, Ji Seung-Hyun, Lee Yu-Bi, Jang Young-Nam | H358: historical, action, melodrama, Drama, romance | I358: retro / period setting, Palace intrigue, Joseon era, Star-Crossed Lovers, tragic separation, right person wrong time, love triangle, enemies to lovers, street fights / hand-to-hand combat, betrayal, sibling's rivalry, alpha / strong FL, protective ML, tragic backstory | J358: ending will destroy you, cry fest, emotional rollercoaster, Intense action, dark & heavy, plot twist heavy, OST is everything | K358: 8.1 | L358: https://pin.it/4K6DraC9J | M358: https://pin.it/330s7ITL8 | N358: Set during the transition between the end of the Goryeo dynasty and the rise of the Joseon era, Seo Hwi is a fierce warrior whose father was executed as a traitor, while Nam Sun-ho is an exceptionally skilled fighter born out of wedlock to a powerful noble family. Once close best friends, their differing ideologies and family burdens push them onto opposing sides of a bloody political revolution.
A359: My dearest | B359: series | C359: Korea | D359: 2023 | E359: 10 | F359: Completed | G359: Namgoong Min, Ahn Eun-Jin, Lee Hak-Joo, Lee Da-In, Kim Yoon-Woo | H359: historical, romance, melodrama, Drama | I359: Joseon era, epic romance, fated / destined love, Star-Crossed Lovers, tragic separation, right person wrong time, slow burn romance, mutual pining, He-Falls-First, protective ML, yearning / lovesick ML, alpha / strong FL, character growth, street fights / hand-to-hand combat, top tier kiss, green flag ML, older ML (oppa), chemistry overload, k-trauma | J359: masterpiece , emotional rollercoaster, cry fest, dark & heavy, aesthetically beautiful, OST is everything, binge-worthy | K359: 8.9 | L359: https://pin.it/5caXJu09R | M359: https://pin.it/6LMiLlirA | N359: Set during the Qing invasion of Joseon, Lee Jang-hyun is a charming, cynical man who has vowed never to commit to marriage, while Yoo Gil-chae is an arrogant, high-society noblewoman who believes every man is at her feet. When the horrors of war tear their peaceful countryside apart, the two fall into a deeply poignant, lingering romance, enduring years of separation, hardship, and devastation across enemy lines.
A360: My dearest nemesis | B360: series | C360: Korea | D360: 2025 | E360: 12 | F360: Completed | G360: Mun Ka-Young, Choi Hyun-Wook, Im Se-Mi, Hwak Shi-Yang | H360: historical, romance, political, Drama | I360: second couple syndrome, workplace romance, CEO x Employee, first love, unresolved feelings, childhood connection / first meeting, older FL (noona), Golden Retriever ML, yearning / lovesick ML, He-Falls-First, hidden true self, Rich x Poor, hate to tolerance to love | J360: plot twist heavy, dark & heavy, fast-paced | K360: 7.3 | L360: https://pin.it/1Dxv8MDPs | M360: https://pin.it/4HMvq8vsQ | N360: Baek Su-jeong is a talented planning-team leader at Yongseong Department Store who is forced to work under her new boss, Ban Ju-yeon. Sixteen years earlier, the two first met through an online game, where Su-jeong developed feelings for the mysterious player known as “Black Dragon.” Their disastrous first meeting left Su-jeong with an embarrassing memory and a grudge. Now, as adults, she discovers that her new boss is actually the same person, forcing them to confront their complicated past while their old feelings resurface.
A361: My demon | B361: series | C361: Korea | D361: 2023 | E361: 16 | F361: Completed | G361: Kim Yoo-Jung, Song Kang, Lee Sang-Yi, Kim Hae-Sook, Jo Hye-Joo | H361: romcom, fantasy, romance, comedy | I361: contract relationship, fake marriage, Co-habitation / living together, forced proximity, enemies to lovers, Human x Supernatural Entity, supernatural abilities / powers, demon / deity, past-life connection, fated / destined love, yearning / lovesick ML, alpha / strong FL, career-driven FL, chaebol family drama, inheritance battle, top tier kiss, love triangle, Golden Retriever ML, chemistry overload | J361: chaotic fun, feel-good, binge-worthy, episode 1 hook, aesthetically beautiful, OST is everything | K361: 7.7 | L361: https://pin.it/2k0oIb1Xt | M361: https://pin.it/1Pfm4QcW9 | N361: Do Do-hee is an arrogant, distrustful heiress to the powerful Future Group who is surrounded by enemies plotting her downfall. Jung Koo-won is a charming demon who has made deals with humans for 200 years, taking their souls upon contract expiration. When Koo-won unexpectedly loses his supernatural powers to Do-hee during a life-threatening accident, he is forced to enter a contract marriage with her to protect her and recover his abilities.
A362: My first first love 1 | B362: series | C362: Korea | D362: 2019 | E362: 8 | F362: Completed | G362: Kim Ji-Soo, Jung Chae-Yeon, Jung Jin-Young, Choi Ri, Kang Tae-Oh, Hong Ji-Yoon | H362: romance, youth, comedy, slice-of-life | I362: Co-habitation / living together, forced proximity, friends to lovers, first love, love triangle, second lead syndrome, He-Falls-First, mutual pining, green flag ML, clumsy FL, friends group, university / campus, adult life struggles | J362: comfort drama, feel-good, easy watch, chaotic fun, underrated gem | K362: 7.4 | L362: https://pin.it/6YMUEJnc9 | M362: https://pin.it/3boUFdvF2 | N362: Yoon Tae-o is a university student whose house becomes a temporary refuge for three of his closest friends due to various personal, financial, and family struggles, including his long-time childhood best friend, Han Song-i. As the five young adults navigate co-habitation, career anxiety, and financial struggles, Tae-o and Song-i must process their evolving feelings as new romantic interests enter their lives.
A363: My first first love 2 | B363: series | C363: Korea | D363: 2019 | E363: 8 | F363: Completed | G363: Kim Ji-Soo, Jung Chae-Yeon, Jung Jin-Young, Choi Ri, Kang Tae-Oh, Hong Ji-Yoon, Park Ji-Hwan | H363: romance, youth, comedy, slice-of-life | I363: Co-habitation / living together, forced proximity, friends to lovers, love triangle, second lead syndrome, unresolved feelings , character growth, coming-of-age journey, adult life struggles, university / campus | J363: feel-good, easy watch, emotional rollercoaster, underrated gem | K363: 7.4 | L363: https://pin.it/3dAce4Swr | M363: https://pin.it/33hJPv4Rn | N363: Picking up as the close-knit housemates navigate their college years, Yoon Tae-o, Han Song-i, and Seo Do-hyeon face the realities of young adulthood, career decisions, and complex romantic choices. As Song-i and Do-hyeon explore their relationship, Tae-o comes to terms with his own suppressed feelings for his childhood friend, testing the bonds of their group dynamic.
A364: My first love | B364: series | C364: Korea | D364: 2018 | E364: 10 | F364: Completed | G364: Lee Jung-Shin, Seo Ji-Hoon, Lee Yeol-Eum | H364: romance, fantasy, youth, school | I364: time travel, highschool setting, school romance, first love, right person wrong time, mutual pining, character growth, secret identity, hidden true self | J364: easy watch, feel-good | K364: 7.1 | L364: https://pin.it/6cJOj3QVq | M364: https://pin.it/5xTWMG6Kw | N364: Kang Shin-woo is a handsome high school math teacher who has spent ten years unable to forget his first love, Han Ji-soo. Through a bizarre twist of fate, he stumbles into a time slip that sends him back ten years into the past, where he encounters his 18-year-old self. Shin-woo takes on the mission of guiding his younger self to win Ji-soo's heart, sparking an awkward rivalry against his own past persona.
... A371: My lovely journey | B371: series | C371: Korea | D371: 2025 | E371: 10 | F371: Completed | G371: Gong Seung-Yeon, Kim Jae-Yeong, Yoo Joon-Sang, Hong Soo-Hyun, Oh Hyun-Joong | H371: slice-of-life, Drama | I371: healing journey, life lessons, adult life struggles, found family, character growth, small town / island setting, overseas / abroad setting, comfort romance, coming-of-age journey, overcoming obstacles, career-driven FL | J371: healing & therapeutic, comfort drama, feel-good, easy watch | K371: 6.5 | L371: https://pin.it/1I9pFj9xD | M371: https://pin.it/1MTa2mwac | N371: An uplifting, scenic travel drama following an ex-idol turned travel vlogger who embarks on a series of meaningful journeys across coastal cities and quiet countrysides. As she documents her travels and interacts with locals carrying their own unspoken burdens, she learns to redefine her identity and find comfort after stepping away from the entertainment world.
A372: My lovely journey 2 | B372: series | C372: Korea | E372: 10 | F372: Upcoming | G372: Gong Seung-Yeon, Yoo Joon-Sang, Kim Jae-Yeong | H372: slice-of-life, Drama | I372: healing journey, life lessons, adult life struggles, found family, character growth, small town / island setting, comfort romance, career-driven FL, village romance, Co-habitation / living together | J372: healing & therapeutic, comfort drama, feel-good, easy watch | L372: https://pin.it/1I9pFj9xD | N372: Continuing her travel series across picturesque destinations, the former idol turned vlogger takes on new assignments that explore deep local traditions, human connections, and personal growth. As her platform grows, she navigates new career choices, unexpected romantic encounters, and the challenge of staying true to herself amidst commercial success.
A373: My lovely liar | B373: series | C373: Korea | D373: 2023 | E373: 16 | F373: Completed | G373: Kim So-Hyun, Hwang Min-Hyun, Seo Ji-Hoon, Yun Ji-On, Lee Si-Woo, Nam Hyeon-Woo, Park Kyung-Hye | H373: romcom, mystery, romance, comedy, Drama | I373: supernatural abilities / powers, neighbours, hidden true self, secret identity, framed for a crime, murder mystery, investigation, serial killer hunt, protective ML, green flag ML, career-driven FL, healing romance, top tier kiss, love triangle, chemistry overload | J373: feel-good, binge-worthy, plot twist heavy, easy watch, comfort drama | K373: 7.3 | L373: https://pin.it/5LWFJ33TI | M373: https://pin.it/1yZaxkY1Q | N373: Mok Sol-hee possesses a supernatural curse that she has turned into a business: she can hear whenever someone is telling a lie. Because of this, she trusts no one and considers her power a burden. Her life changes when she becomes neighbors with Kim Do-ha, a genius music producer who went into hiding after being falsely accused of murder years ago, becoming the only person whose words she hears as absolute truth.
A374: My man is cupid | B374: series | C374: Korea | D374: 2023 | E374: 16 | F374: Completed | G374: Jang Dong-Yoon, Nana, Park Ki-Woong, Moon ji-Hoo, Park Myung-Hoon | H374: romcom, fantasy, romance, mystery, comedy | I374: Human x Supernatural Entity, demon / deity, supernatural abilities / powers, curse / spell, past-life connection, fated / destined love, serial killer hunt, investigation, forced proximity, protective ML, clumsy FL, alpha / strong FL, top tier kiss, chemistry overload | J374: chaotic fun, feel-good, binge-worthy, underrated gem | K374: 7.2 | L374: https://pin.it/3mJBb0KLx | M374: https://pin.it/2ko04ZLug | N374: Cheon Sang-hyuk is a charismatic fairy who accidentally burned his own wings 500 years ago, forcing him to live through human reincarnations to restore them. Oh Baek-ryun is a talented veterinary surgeon whose romantic life is a disaster because every man who gets close to her suffers a near-fatal accident. When Sang-hyuk accidentally shoots himself with his own arrow, he falls in love with Baek-ryun, entangling them in a centuries-old curse.
A375: My mister | B375: series | C375: Korea | D375: 2018 | E375: 16 | F375: Completed | G375: Lee Sun-Kyun, IU, Park Ho-San, Song Sae-Byuk, Lee Ji-Ah, Kim Young-Min, Kwon Nara, Jang Ki-Yong, Park Hae-Joon, Oh Na-Ra | H375: Drama, slice-of-life, psychological, melodrama | I375: healing romance, comfort romance, age gap romance, Bittersweet / Realistic romance, slow burn romance, Rich x Poor, undercover, workplace setting, family dynamics, neighborhood squad, found family, adult life struggles, grief & loss, life lessons, overcoming trauma, character growth, tragic backstory, betrayal, character driven | J375: masterpiece , healing & therapeutic, cry fest, emotional rollercoaster, dark & heavy, "slow starter, worth it", OST is everything, underrated gem | K375: 9 | L375: https://pin.it/4I0gTdiMa | M375: https://pin.it/5I2XcylXX | N375: Lee Ji-an is a cold, deeply indebted young woman struggling to care for her disabled grandmother while enduring exploitative working conditions at a structural engineering firm. Dong-hoon is a gentle, middle-aged engineering manager who quietly suffers through a stagnant career and his wife's secret infidelity. Drawn together by their shared exhaustion, the two form a quiet bond that offers them healing and comfort.
A376: My name | B376: series | C376: Korea | D376: 2021 | E376: 8 | F376: Completed | G376: Han So-Hee, Park Hee-Soon, Ahn Bo-Hyun, Lee Hak-Joo, Kim Sang-Ho, Chang Ryul, Moon Sang-Min | H376: action, thriller, crime | I376: undercover, undercover agent / cop, hidden true self, secret identity, revenge, betrayal, gangsters / mafia, dark justice, vigilante justice, street fights / hand-to-hand combat, partners in crime, alpha / strong FL, protective ML, tragic backstory, investigation, epic romance, chemistry overload, k-trauma | J376: episode 1 hook, binge-worthy, fast-paced, Intense action, gory & violent, dark & heavy, plot twist heavy | K376: 7.8 | L376: https://pin.it/60mNnEljS | M376: https://pin.it/21xBn1DUd | N376: Yoon Ji-woo is a teenager who witnesses the brutal murder of her father, a high-ranking mobster. Driven by a desire for revenge, she places her trust in Choi Mu-jin, her father's powerful crime boss, who trains her in hand-to-hand combat and helps her infiltrate the police department under an assumed identity. Operating as a mole in the narcotics unit, she works to identify her father's killer while keeping her cover intact.
A377: My perfect stranger | B377: series | C377: Korea | D377: 2023 | E377: 16 | F377: Completed | G377: Kim Dong-Wook, Jin Ki-Joo, Seo Ji-Hye, Lee Won-Jung | H377: mystery, fantasy, sci-fi, thriller, Drama | I377: time travel, 1980s setting, retro / period setting, highschool setting, murder mystery, serial killer hunt, investigation, cat-and-mouse chase, secret past revealed, tragic backstory, family dynamics, partners in crime, protective ML, career-driven FL, no romance, second couple syndrome | J377: plot twist heavy, episode 1 hook, binge-worthy, fast-paced, dark & heavy, underrated gem | K377: 8 | L377: https://pin.it/1igxQQX3V | M377: https://pin.it/KgUwJwNhj | N377: Yoon Hae-jun, a cool-headed news anchor, and Baek Yoon-young, an overworked publishing employee, acquire a time-traveling car that unexpectedly strands them both back in the year 1987. While Hae-jun tries to solve a past serial murder case that connects to his own future death, Yoon-young attempts to stop her teenage parents from marrying to save her mother, discovering that their separate missions are interconnected.
A378: My roommate is a gumiho | B378: series | C378: Korea | D378: 2021 | E378: 16 | F378: Completed | G378: Jang Ki-Yong, Lee Hye-Ri, Kang Han-Na, Kim Do-Wan, Bae In-Hyuk, Choi Woo-Sung, Park Kyung-Hye | H378: romcom, fantasy, romance, comedy | I378: Nine-Tailed Fox (Gumiho), Human x Supernatural Entity, supernatural abilities / powers, magical element, Co-habitation / living together, forced proximity, university / campus, contract relationship, cold / tsundere ML, protective ML, yearning / lovesick ML, clumsy FL, alpha / strong FL, second couple syndrome, top tier kiss, webtoon adaptation, She-Falls-First, chemistry overload, Teacher x Student | J378: chaotic fun, feel-good, easy watch, binge-worthy, rewatchable | K378: 7.6 | L378: https://pin.it/2og6po1i6 | M378: https://pin.it/5pbmHUvTM | N378: Shin Woo-yeo is a handsome 999-year-old nine-tailed fox who needs to fill his mystical marble with human energy before reaching 1,000 years to become human. Lee Dam, a quirky college student, accidentally swallows his precious marble during a drunk encounter. To protect the marble and figure out how to extract it safely without harming her life, the two move in together, leading to a supernatural co-habitation romance.
A379: My royal nemesis | B379: series | C379: Korea | D379: 2026 | E379: 12 | F379: Completed | G379: Im Ji-Yeon, Heo Nam-Jun, Jang Seung-Jo, Kim Min-Seok, Lee Se-Hee, Kim Hae-Sook, Baek ji-Won, Chae Seo-An, Jung Young-Joo, Yoon Byung-Hee | H379: romcom, political, comedy, romance | I379: enemies to lovers, cold / tsundere ML, alpha / strong FL, yearning / lovesick ML, chemistry overload, time travel, reincarnation, secret identity, Rich x Poor, chaebol family drama, past-life connection | J379: chaotic fun, feel-good, easy watch | K379: 7.5 | L379: https://pin.it/4neaYwywY | M379: https://pin.it/4aGvfCUI2 | N379: After being sentenced to death in Joseon, the legendary villainess Kang Dan-sim mysteriously awakens in 2026 Seoul inside the body of struggling actress Shin Seo-ri. Struggling to adapt to the modern world, she repeatedly clashes with Cha Se-gye, the arrogant and calculating heir to a powerful conglomerate. Their love-hate relationship gives Dan-sim an unexpected chance to escape the fate that once awaited her.
A380: My secret romance | B380: series | C380: Korea | D380: 2017 | E380: 13 | F380: Completed | G380: Sung Hoon, Song Ji-Eun, Kim Jae-Yeong, Jung Da-Sol | H380: romcom, romance, comedy | I380: workplace romance, CEO x Employee, Rich x Poor, forced proximity, cold / tsundere ML, protective ML, clumsy FL, secret dating, top tier kiss, chemistry overload | J380: feel-good, easy watch, rewatchable, chaotic fun | K380: 7.1 | L380: https://pin.it/4DdurCERC | M380: https://pin.it/vh9Fs9eH3 | N380: Cha Jin-wook, a wealthy, playboy heir to a major corporation, and Lee Yoo-mi, a sweet, insecure woman who has never dated, share a passionate one-night stand at a coastal resort before vanishing from each other's lives. Three years later, they are unexpectedly reunited when Yoo-mi is hired as the personal nutritionist at Jin-wook's company, forcing them to navigate their awkward history and unresolved feelings.
A381: My secret terrius | B381: series | C381: Korea | D381: 2018 | E381: 32 | F381: Completed | G381: So Ji-Sub, Jung In-Sun, Son Ho-Jun, Im Se-Mi | H381: comedy, action, thriller, mystery, crime, Drama | I381: double life, hidden true self, secret identity, neighbours, single parent, protective ML, green flag ML, alpha / strong FL, partners in crime, Ajummas lead (middle-aged women), neighborhood squad, investigation, dark comedy, no romance | J381: chaotic fun, feel-good, comfort drama, easy watch, binge-worthy, underrated gem | K381: 7.6 | L381: https://pin.it/3TuIRq7Xk | M381: https://pin.it/4aDny2PWL | N381: Go Ae-rin is a widowed mother of twins who finds herself unexpectedly caught in a covert national security crisis when her husband is murdered. Kim Bon, her quiet, mysterious next-door neighbor, is actually an elite legendary NIS black-ops agent living in hiding after a failed operation. To uncover the conspiracy behind her husband's death, Kim Bon becomes the full-time babysitter for her energetic children, balancing espionage with domestic life.
A382: My shy boss | B382: series | C382: Korea | D382: 2017 | E382: 16 | F382: Completed | G382: Yeon Woo-Jin, Park Hye-Soo, Yoon Park, Gong Seung-Yeon | H382: romcom, Drama | I382: introvert x extrovert , cold / tsundere ML, CEO x Employee, secret identity, overcoming trauma, workplace romance, workplace setting, Co-habitation / living together, secret past revealed, second lead syndrome, workplace team bond | J382: easy watch, healing & therapeutic, "slow starter, worth it" | K382: 7.1 | L382: https://pin.it/4dauMUTea | M382: https://pin.it/6o8N6sTGP | N382: Eun Hwan-ki is the CEO of a top public relations agency, but he is extremely shy and introverted to the point where even his employees view him as a cold, terrifying phantom. When an energetic, outgoing new employee joins the company to secretly avenge her sister’s suspicious suicide, she vows to expose Hwan-ki’s true face, only to fall for the gentle man beneath the shell.
A383: My strange hero | B383: series | C383: Korea | D383: 2018 | E383: 16 | F383: Completed | G383: Yoo Seung-Ho, Jo Bo-Ah, Kwak Dong-Yeon | H383: romcom, Drama, school, romance, comedy | I383: second chance romance, highschool setting, adult returning to highschool, school corruption, Underdog vs. Elite, academic pressure, contract relationship, workplace romance, school romance, Teacher x Student, first love, right person wrong time, framed for a crime, school bullying, revenge, protective ML, alpha / strong FL, top tier kiss, chemistry overload, hate to tolerance to love | J383: feel-good, emotional rollercoaster, chaotic fun, binge-worthy | K383: 7.4 | L383: https://pin.it/21DM19xIo | M383: https://pin.it/4hfwi6Y3w | N383: Kang Bok-soo was falsely accused of violence and expelled from high school years ago due to the betrayals of his first love, Son Soo-jeong, and a wealthy classmate, Oh Se-ho. Now an adult taking on random odd jobs, Bok-soo gets the opportunity to return to his old high school as a mature student to seek revenge. However, he finds the school corrupt and his former first love working there as a teacher, shifting his goal toward protection and reform.
...

Sheet Movies Database
A1: DRAMOIR · Drama Database
A2: Title | B2: type | C2: country | D2: year | E2: Genres | F2: Tropes | G2: Mood / Vibe Tags | H2: Global Rating (/10) | I2: Poster URL | J2: Banner URL | K2: Synopsis
A3: #Alive | B3: movie
A4: 18×2 beyond youthful days | B4: movie
A5: 1987: when the day comes | B5: movie
A6: 20th century girl | B6: movie
A7: a little red flower | B7: movie
A8: a man and a woman | B8: movie
A9: a werewolf boy | B9: movie
A10: a year -end medley | B10: movie
A11: after my death | B11: movie
A12: almost love | B12: movie
A13: always | B13: movie
A14: badland hunters | B14: movie
... A22: colony | B22: movie
A23: Concrete market | B23: movie | H23: 5.2
A24: concrete utopia | B24: movie
A25: confession | B25: movie
A26: confidential assignment | B26: movie
A27: confidential assignment 2: international | B27: movie
A28: cry me a sad river | B28: movie
A29: D-day | B29: movie
A30: dark nuns | B30: movie
A31: ditto | B31: movie
A32: door lock | B32: movie
A33: drawing closer | B33: movie
A34: dream | B34: movie
A35: emergency declaration | B35: movie
... A164: A diamond in the rough | B164: movie
B165: movie

Sheet reality shows Database 
A1: DRAMOIR · Drama Database
A2: Title | B2: type | C2: country | D2: Year | E2: Mood / Vibe Tags | F2: Global Rating (/10) | G2: Poster URL | H2: Banner URL | I2: Synopsis

Sheet JDrama Database 
A2: Title | B2: type | C2: country | D2: Year | E2: Episodes | F2: Status | G2: Cast | H2: Genres | I2: Tropes | J2: Mood / Vibe Tags | K2: Global Rating (/10) | L2: Poster URL | M2: Banner URL | N2: Synopsis

Sheet CDrama Database 
A2: Title | B2: type | C2: country | D2: Year | E2: Episodes | F2: Status | G2: Cast | H2: Genres | I2: Tropes | J2: Mood / Vibe Tags | K2: Global Rating (/10) | L2: Poster URL | M2: Banner URL | N2: Synopsis

Sheet 🎞️ Genres
A1: DRAMOIR · Genres — 26 genres
A2: Genre | B2: Notes / Description
A3: romcom
A4: comedy
A5: romance
A6: Drama
A7: melodrama
A8: fantasy
A9: historical
A10: slice-of-life
A11: youth
A12: action
A13: crime
A14: thriller
... A27: family

Sheet 🎭 Tropes
A1: DRAMOIR · Tropes Reference — 274 tropes · 21 categories
A2: Category | B2: Trope
A3: ❤️ How They Fall | B3: hate to tolerance to love
B4: enemies to lovers
B5: friends to lovers
B6: love at first sight
B7: He-Falls-First
B8: She-Falls-First
B9: mutual pining
A10: 💍 Relationship Setups | B10: fake dating
B11: fake marriage
B12: contract relationship
B13: Co-habitation / living together
B14: forced proximity
B15: secret dating
B16: age gap romance
B17: toxic relationship
B18: right person wrong time
A19: 💕 Romance Foundations | B19: epic romance
B20: fated / destined love
B21: forbidden love
B22: unrequited love
B23: first love
B24: Star-Crossed Lovers
B25: second chance romance
B26: unresolved feelings
B27: tragic separation
B28: love triangle
B29: second lead syndrome
B30: second lead breaks your heart
B31: second couple syndrome
A32: 🌸 Romance Styles & Tones | B32: comfort romance
B33: healing romance
B34: mature romance
B35: Bittersweet / Realistic romance
B36: dark romance
B37: slow burn romance
B38: workplace romance
B39: school romance
B40: village romance
B41: tech-driven romance
A42: 💋 Iconic Physical Moments | B42: chemistry overload
B43: THE confrontation
B44: top tier kiss
A45: ⚡ Personality Pairings & Dynamics | B45: introvert x extrovert
B46: calm x calm
B47: Calm x Chaotic
B48: Chaotic x Chaotic
B49: grumpy x sunshine
B50: Rich x Poor
B51: CEO x Employee
B52: Celebrity x Normal Citizen
B53: Teacher x Student
B54: K-pop Idol life
B55: single parent
A56: 🧑 Male Lead Archetypes | B56: cold / tsundere ML
B57: protective ML
B58: Golden Retriever ML
B59: yearning / lovesick ML
B60: green flag ML
B61: red flag ML
B62: older ML (oppa)
A63: 👩 Female Lead Archetypes | B63: alpha / strong FL
B64: career-driven FL
B65: naive / innocent FL
B66: emotionally guarded FL
B67: clumsy FL
B68: red flag FL
B69: older FL (noona)
A70: 👥 Group & Community | B70: partners in crime
B71: bromance steals the show
B72: bromance
B73: sisterhood
B74: found family
B75: friends group
B76: neighborhood squad
B77: underdog squad
B78: workplace team bond
B79: Ajummas lead (middle-aged women)
A80: 🌱 Growth & Healing | B80: coming-of-age journey
B81: healing journey
B82: character growth
B83: overcoming obstacles
B84: overcoming trauma
B85: childhood trauma
B86: grief & loss
B87: life lessons
B88: adult life struggles
A89: 🎬 Crime, Mystery & Investigation | B89: murder mystery
B90: serial killer hunt
B91: investigation
B92: accidental murder / witness
B93: framed for a crime
B94: cat-and-mouse chase
B95: psychopathic villain
B96: mind games / psychological warfare
A97: ⚔️ Action & Thriller | B97: cops / police
B98: gangsters / mafia
B99: heist / robbery
B100: Heroic Save
...

Sheet ✨ Mood & Vibe Tags
A1: DRAMOIR · Mood & Vibe Tags — 27 tags
A2: Mood / Vibe Tag | B2: Description
A3: comfort drama | B3: Easy, warm, no stress — perfect to rewatch
A4: feel-good | B4: Leaves you happy and warm
A5: healing & therapeutic | B5: Calming, restorative feeling
A6: emotional rollercoaster | B6: Lots of highs and lows
A7: cry fest | B7: Prepare tissues
A8: easy watch | B8: Low effort, fun and light
A9: rewatchable | B9: Worth watching again
A10: binge-worthy | B10: Can't stop watching, fast pacing
A11: episode 1 hook
A12: fast-paced
A13: slow starter, worth it | B13: Needs a few episodes to pick up
A14: masterpiece
A15: underrated gem | B15: Deserves more attention
A16: ending will destroy you | B16: The finale hits hard
A17: disappointing ending
A18: classic | B18: A must-watch in kdrama history
A19: chaotic fun | B19: Crazy plot but in a good way
A20: Intense action
A21: gory & violent
A22: plot twist heavy | B22: Shocking revelations throughout
A23: dark & heavy | B23: Intense, not for light watching
A24: aesthetically beautiful | B24: Stunning cinematography / visuals
A25: OST is everything | B25: Soundtrack is a highlight
